{"labels": {"2": [1, 1, 1, 1, 1, 1, 1, 1, 1, 1, 1, 1, 1, 1, 1, 1, 1, 1, 1, 1, 1, 1, 1, 1, 1, 1, 1, 1, 1, 1, 1, 1, 1, 1, 1, 1, 1, 1, 1, 1, 1, 1, 1, 1, 1, 1, 1, 1, 1, 1, 1, 1, 1, 1, 1, 1, 1, 1, 1, 1, 1, 1, 1, 1, 1, 1, 1, 1, 1, 1, 1, 1, 1, 1, 0, 1, 1, 1, 1, 1, 1, 1, 1, 1, 1, 1, 1, 1, 0, 0, 0, 0, 1, 1, 1, 1, 1, 1, 1, 1, 1, 1, 1, 1, 1, 1, 0, 0, 0, 0, 0, 0, 0, 0, 0, 1, 1, 1, 1, 1, 0, 0, 1, 1, 1, 1, 0, 1, 0, 0, 1, 1, 0, 0, 1, 0, 0, 0, 0, 1, 1, 0, 0, 0, 0, 0, 0, 1, 0, 0, 0, 0, 0, 0, 0, 0, 0, 0, 0, 0, 0, 0, 0, 0, 0, 0, 0, 0, 0, 0, 0, 0, 0, 0, 0, 0, 0, 0, 0, 0, 0, 0, 0, 0, 0, 0, 0, 0, 0, 0, 0, 0, 0, 0, 0, 0, 0, 0, 0, 0, 0, 0, 0, 0, 0, 0, 0, 0, 0, 0, 0, 0, 0, 0, 0, 0, 0, 0, 0, 0, 0, 0, 0, 0, 0, 0, 0, 0, 0, 0, 0, 1, 0, 0, 0, 0, 0, 0, 0, 0, 0, 0, 0, 0, 1, 0, 0, 1, 1, 0, 1, 0, 0, 0, 0, 0, 0, 0, 0, 0, 0, 0, 0, 0, 0, 1, 1, 0, 0, 0, 0, 0, 0, 0, 1, 1, 1, 1, 1, 1, 1, 1, 1, 1, 0, 0, 0, 1, 1, 1, 1, 1, 1, 1, 1, 1, 1, 1, 1, 1, 1, 1, 1, 1, 1, 1, 1, 1, 1, 1, 1, 1, 1, 1, 1, 1, 1, 1, 1, 1, 1, 1, 1, 1, 1, 1, 1, 1, 1, 1, 1, 1, 1, 1, 1, 1, 1, 1, 1, 1, 1, 1, 1, 1, 1, 1, 1, 1, 1, 1, 1, 1, 1, 1, 1, 1, 1, 1, 1, 1, 1, 1, 1, 1, 1], "3": [2, 2, 2, 2, 2, 2, 2, 2, 2, 2, 2, 2, 2, 2, 2, 2, 2, 2, 2, 2, 2, 2, 2, 2, 2, 2, 2, 2, 2, 2, 2, 2, 2, 2, 2, 2, 2, 2, 2, 2, 2, 2, 2, 2, 2, 2, 2, 2, 2, 2, 2, 2, 2, 2, 2, 2, 2, 1, 1, 2, 2, 1, 2, 2, 2, 2, 2, 2, 1, 2, 2, 2, 2, 2, 1, 1, 2, 2, 2, 2, 1, 1, 1, 2, 2, 2, 1, 1, 1, 1, 1, 1, 1, 2, 2, 1, 1, 1, 1, 2, 2, 2, 2, 2, 1, 1, 1, 1, 1, 1, 1, 1, 1, 1, 1, 2, 1, 2, 2, 1, 1, 1, 1, 2, 2, 2, 1, 2, 1, 1, 1, 1, 1, 1, 1, 1, 1, 1, 1, 1, 1, 1, 0, 0, 1, 0, 0, 1, 1, 0, 0, 0, 0, 0, 0, 0, 1, 0, 0, 1, 1, 1, 1, 0, 0, 0, 0, 0, 0, 0, 0, 0, 1, 0, 0, 0, 0, 0, 0, 0, 0, 0, 0, 0, 0, 0, 0, 0, 0, 0, 0, 0, 1, 0, 0, 0, 0, 0, 0, 0, 0, 0, 0, 0, 0, 0, 0, 0, 1, 0, 0, 0, 0, 1, 0, 0, 0, 1, 1, 0, 0, 1, 0, 1, 1, 0, 1, 0, 1, 0, 1, 1, 1, 1, 1, 1, 0, 0, 0, 0, 0, 0, 0, 1, 1, 1, 1, 1, 1, 1, 1, 1, 1, 1, 1, 1, 1, 1, 0, 1, 1, 1, 1, 1, 1, 1, 1, 1, 1, 1, 1, 1, 1, 1, 1, 1, 2, 1, 1, 1, 1, 1, 1, 1, 1, 1, 1, 1, 1, 1, 1, 1, 1, 1, 1, 1, 1, 1, 1, 1, 1, 2, 2, 2, 2, 1, 1, 1, 2, 2, 2, 2, 2, 2, 2, 2, 2, 2, 2, 2, 2, 2, 2, 2, 2, 2, 2, 2, 2, 2, 2, 2, 2, 2, 2, 2, 2, 2, 2, 2, 2, 2, 2, 2, 2, 2, 2, 2, 1, 2, 2, 2, 2, 2, 2, 2, 2, 2, 2, 2, 2, 2, 2, 2, 2], "4": [0, 0, 0, 0, 0, 0, 0, 0, 0, 0, 0, 0, 0, 0, 0, 0, 0, 0, 0, 0, 0, 0, 0, 0, 0, 0, 0, 0, 0, 0, 0, 0, 0, 0, 0, 0, 0, 0, 0, 3, 0, 0, 0, 0, 0, 0, 0, 3, 3, 3, 3, 3, 3, 0, 0, 3, 3, 3, 3, 0, 3, 3, 3, 3, 3, 3, 3, 3, 3, 0, 3, 0, 0, 3, 3, 3, 0, 0, 3, 3, 3, 3, 3, 3, 0, 3, 3, 3, 3, 3, 3, 3, 3, 0, 0, 3, 3, 3, 3, 3, 3, 3, 3, 0, 3, 3, 3, 1, 1, 1, 1, 1, 1, 1, 1, 3, 3, 3, 3, 3, 3, 3, 3, 3, 0, 3, 3, 3, 3, 3, 3, 3, 3, 3, 3, 3, 1, 1, 1, 3, 3, 1, 2, 2, 1, 2, 1, 3, 3, 2, 2, 2, 2, 2, 2, 2, 1, 1, 2, 1, 3, 1, 1, 2, 2, 1, 2, 2, 2, 2, 2, 2, 1, 2, 2, 2, 2, 2, 2, 2, 2, 2, 2, 2, 2, 2, 2, 1, 2, 2, 2, 2, 1, 2, 2, 1, 2, 2, 2, 2, 2, 2, 2, 2, 2, 2, 2, 1, 1, 1, 2, 1, 1, 1, 1, 2, 1, 1, 1, 1, 2, 1, 1, 1, 1, 1, 1, 1, 1, 1, 1, 3, 1, 1, 1, 1, 1, 1, 1, 1, 1, 1, 1, 1, 3, 1, 1, 3, 3, 3, 3, 3, 1, 1, 1, 1, 1, 1, 1, 1, 3, 3, 3, 3, 1, 3, 3, 3, 3, 1, 1, 1, 1, 1, 3, 3, 3, 3, 3, 3, 3, 3, 3, 3, 3, 1, 1, 3, 3, 3, 3, 3, 3, 3, 3, 3, 3, 3, 3, 3, 3, 0, 0, 0, 3, 3, 3, 3, 3, 3, 0, 0, 0, 0, 0, 0, 0, 0, 0, 0, 0, 0, 0, 0, 0, 0, 0, 0, 0, 0, 3, 3, 0, 0, 0, 0, 0, 0, 0, 0, 3, 3, 0, 0, 0, 0, 0, 0, 3, 0, 0, 3, 0, 0, 0, 0, 0, 0, 0, 0, 0, 0, 0, 0, 0], "5": [3, 3, 3, 3, 3, 3, 3, 3, 3, 3, 3, 3, 3, 3, 3, 3, 3, 3, 3, 3, 3, 3, 3, 3, 3, 3, 3, 3, 3, 3, 3, 3, 3, 3, 3, 3, 3, 3, 3, 4, 4, 3, 3, 3, 3, 3, 3, 0, 0, 4, 0, 0, 4, 3, 3, 0, 0, 0, 0, 4, 4, 0, 4, 0, 0, 4, 4, 4, 4, 3, 0, 3, 3, 4, 0, 4, 3, 3, 0, 0, 0, 0, 0, 0, 0, 0, 0, 0, 0, 0, 0, 0, 0, 3, 3, 0, 0, 0, 4, 4, 4, 0, 0, 3, 0, 0, 0, 1, 1, 1, 1, 1, 1, 1, 1, 4, 0, 0, 0, 4, 0, 0, 4, 4, 3, 0, 0, 4, 0, 0, 4, 0, 0, 0, 0, 0, 0, 1, 1, 4, 4, 1, 2, 2, 1, 2, 2, 4, 0, 2, 2, 2, 2, 2, 2, 2, 1, 1, 2, 1, 4, 1, 1, 2, 2, 1, 2, 2, 2, 2, 2, 2, 1, 2, 2, 2, 2, 2, 2, 2, 2, 2, 2, 2, 2, 2, 2, 1, 2, 2, 2, 2, 1, 2, 2, 1, 2, 2, 2, 2, 2, 2, 2, 2, 2, 2, 2, 1, 1, 1, 2, 1, 2, 1, 1, 2, 1, 1, 1, 1, 2, 1, 1, 1, 1, 1, 1, 1, 1, 1, 1, 4, 1, 1, 1, 1, 1, 1, 1, 1, 1, 1, 1, 1, 4, 1, 1, 4, 4, 1, 4, 0, 1, 1, 1, 1, 1, 1, 1, 1, 1, 0, 0, 0, 1, 4, 4, 4, 4, 1, 1, 1, 1, 1, 4, 0, 4, 4, 4, 4, 4, 4, 4, 0, 1, 1, 1, 4, 0, 4, 4, 4, 4, 4, 4, 4, 4, 4, 4, 4, 4, 4, 4, 4, 4, 4, 4, 4, 4, 4, 3, 3, 3, 3, 3, 3, 3, 3, 3, 3, 3, 3, 3, 3, 3, 3, 3, 4, 3, 4, 4, 4, 4, 3, 3, 3, 3, 3, 3, 3, 4, 4, 4, 3, 3, 3, 3, 4, 4, 3, 4, 4, 3, 3, 3, 3, 3, 3, 3, 3, 3, 3, 3, 3, 3], "6": [0, 0, 0, 0, 0, 0, 0, 0, 0, 0, 0, 0, 0, 0, 0, 0, 0, 0, 0, 0, 0, 0, 0, 0, 0, 0, 0, 0, 0, 0, 0, 0, 0, 0, 0, 0, 0, 0, 0, 2, 2, 0, 0, 0, 0, 0, 0, 5, 5, 2, 2, 5, 2, 0, 0, 5, 5, 5, 5, 2, 2, 5, 2, 2, 2, 2, 2, 2, 2, 0, 5, 0, 0, 2, 5, 2, 0, 0, 5, 5, 5, 5, 5, 5, 5, 5, 5, 5, 5, 5, 5, 5, 5, 0, 0, 5, 5, 5, 2, 2, 2, 5, 5, 0, 5, 5, 5, 4, 4, 4, 4, 4, 4, 4, 5, 2, 5, 5, 5, 2, 5, 5, 2, 2, 0, 5, 5, 2, 5, 5, 1, 5, 5, 5, 5, 5, 5, 4, 5, 2, 2, 4, 4, 3, 1, 4, 4, 1, 5, 4, 4, 3, 3, 3, 3, 3, 1, 4, 4, 1, 1, 1, 4, 3, 3, 4, 4, 3, 3, 3, 4, 3, 1, 3, 3, 3, 3, 3, 3, 3, 3, 3, 3, 3, 3, 3, 3, 4, 4, 4, 3, 4, 4, 4, 4, 4, 3, 3, 4, 3, 3, 4, 3, 3, 3, 3, 3, 4, 1, 4, 4, 4, 4, 4, 4, 4, 4, 1, 1, 4, 4, 1, 4, 1, 4, 4, 1, 4, 1, 4, 1, 1, 1, 1, 1, 4, 4, 4, 4, 4, 4, 4, 4, 1, 1, 4, 4, 1, 1, 1, 2, 5, 5, 1, 4, 4, 4, 4, 4, 1, 1, 5, 5, 5, 1, 1, 1, 1, 1, 1, 1, 1, 1, 1, 1, 5, 2, 2, 2, 5, 1, 2, 1, 5, 1, 1, 1, 2, 5, 1, 1, 1, 1, 1, 1, 1, 1, 1, 2, 1, 2, 2, 2, 2, 2, 1, 2, 2, 2, 2, 2, 0, 0, 0, 0, 2, 0, 0, 0, 0, 0, 0, 0, 0, 0, 0, 2, 2, 2, 2, 2, 2, 2, 0, 0, 0, 0, 0, 0, 0, 2, 2, 2, 0, 0, 0, 0, 2, 2, 2, 2, 2, 2, 2, 2, 2, 2, 2, 2, 0, 2, 0, 0, 0, 0], "7": [1, 1, 1, 1, 1, 1, 1, 1, 1, 1, 1, 1, 1, 1, 1, 1, 5, 1, 1, 1, 1, 1, 1, 1, 1, 1, 1, 1, 1, 1, 1, 1, 1, 1, 1, 1, 1, 1, 1, 5, 5, 1, 1, 1, 3, 3, 3, 3, 3, 3, 3, 3, 5, 3, 3, 3, 3, 3, 3, 5, 5, 3, 5, 3, 3, 5, 5, 5, 5, 1, 3, 3, 1, 5, 4, 5, 3, 3, 3, 3, 3, 4, 4, 3, 3, 3, 3, 4, 4, 4, 4, 4, 3, 1, 3, 3, 3, 3, 3, 5, 5, 3, 3, 1, 3, 4, 4, 4, 4, 4, 4, 4, 4, 4, 4, 5, 3, 3, 3, 5, 4, 4, 5, 5, 3, 3, 4, 5, 4, 4, 0, 3, 4, 4, 4, 4, 4, 4, 4, 0, 0, 4, 6, 2, 0, 6, 6, 0, 4, 4, 6, 2, 2, 2, 2, 2, 0, 4, 6, 0, 0, 0, 6, 2, 2, 6, 6, 2, 2, 2, 6, 2, 0, 2, 2, 2, 2, 2, 2, 2, 2, 2, 2, 2, 2, 2, 2, 6, 6, 6, 2, 6, 6, 6, 6, 6, 2, 6, 6, 6, 6, 6, 6, 2, 2, 6, 6, 6, 0, 6, 6, 6, 6, 6, 6, 6, 6, 0, 0, 6, 6, 0, 6, 0, 4, 6, 0, 6, 0, 6, 0, 0, 4, 0, 0, 6, 6, 6, 6, 6, 6, 6, 6, 0, 0, 4, 6, 0, 0, 0, 5, 4, 4, 4, 6, 6, 0, 6, 6, 0, 0, 4, 4, 4, 0, 0, 0, 0, 0, 0, 0, 0, 0, 0, 0, 3, 5, 0, 5, 0, 0, 0, 0, 3, 0, 0, 0, 0, 0, 0, 0, 0, 0, 0, 0, 0, 0, 0, 0, 0, 5, 5, 5, 5, 5, 0, 5, 5, 5, 5, 5, 5, 5, 1, 1, 5, 1, 1, 1, 1, 1, 5, 1, 5, 5, 1, 5, 5, 5, 5, 5, 5, 5, 1, 1, 1, 1, 1, 1, 1, 5, 5, 5, 1, 1, 1, 1, 5, 5, 5, 5, 5, 5, 5, 5, 5, 5, 5, 5, 1, 5, 1, 1, 1, 1], "8": [0, 0, 0, 0, 0, 0, 0, 0, 0, 0, 0, 0, 0, 0, 0, 0, 3, 0, 0, 0, 0, 0, 0, 0, 0, 0, 0, 0, 0, 0, 0, 0, 0, 0, 0, 0, 0, 0, 5, 3, 3, 0, 0, 0, 5, 5, 5, 5, 5, 5, 5, 5, 3, 5, 5, 5, 5, 5, 6, 3, 3, 5, 3, 5, 5, 3, 3, 3, 3, 0, 5, 5, 0, 3, 6, 3, 5, 5, 5, 5, 6, 6, 6, 5, 5, 5, 6, 6, 6, 6, 6, 6, 6, 0, 5, 5, 6, 6, 3, 3, 3, 5, 5, 0, 5, 6, 6, 6, 6, 4, 4, 4, 4, 4, 6, 3, 5, 5, 5, 3, 6, 6, 3, 3, 5, 5, 6, 3, 6, 6, 7, 6, 6, 6, 6, 6, 6, 6, 6, 7, 7, 1, 1, 1, 7, 1, 1, 7, 6, 1, 1, 2, 2, 2, 2, 2, 1, 1, 1, 1, 7, 7, 1, 1, 2, 4, 1, 2, 2, 2, 1, 1, 7, 2, 2, 2, 2, 2, 2, 2, 2, 2, 2, 2, 2, 2, 2, 4, 1, 1, 1, 1, 4, 1, 1, 1, 2, 2, 4, 2, 2, 4, 2, 2, 2, 2, 2, 4, 7, 4, 4, 4, 4, 4, 4, 4, 4, 7, 7, 4, 4, 4, 4, 7, 4, 4, 4, 4, 4, 4, 4, 7, 4, 7, 4, 4, 4, 4, 4, 4, 4, 4, 4, 7, 7, 6, 4, 7, 7, 7, 3, 6, 6, 6, 4, 4, 4, 4, 4, 4, 7, 6, 6, 6, 7, 7, 7, 7, 7, 7, 7, 4, 7, 6, 7, 5, 3, 7, 3, 7, 7, 7, 7, 6, 7, 7, 7, 7, 7, 7, 7, 7, 7, 7, 7, 7, 7, 7, 7, 7, 3, 3, 3, 3, 3, 7, 3, 3, 3, 3, 3, 3, 3, 0, 0, 3, 0, 0, 0, 0, 0, 3, 0, 3, 0, 0, 3, 3, 3, 3, 3, 3, 3, 0, 0, 0, 0, 0, 0, 0, 3, 3, 3, 0, 0, 0, 0, 3, 3, 3, 3, 3, 3, 3, 3, 3, 3, 3, 3, 0, 3, 0, 0, 0, 0], "9": [0, 0, 0, 0, 0, 0, 0, 0, 0, 0, 0, 0, 0, 0, 0, 0, 2, 0, 0, 0, 0, 0, 0, 0, 0, 0, 0, 0, 0, 0, 0, 0, 0, 0, 0, 0, 0, 0, 0, 2, 2, 0, 0, 0, 8, 8, 8, 8, 8, 8, 8, 8, 2, 8, 8, 8, 8, 8, 8, 2, 2, 8, 2, 8, 8, 2, 2, 2, 2, 0, 8, 8, 0, 2, 3, 2, 8, 8, 8, 8, 8, 3, 3, 8, 8, 8, 8, 3, 3, 3, 3, 3, 3, 0, 8, 8, 3, 8, 2, 2, 2, 8, 8, 0, 8, 3, 3, 3, 3, 3, 6, 6, 6, 3, 3, 2, 8, 8, 8, 2, 3, 3, 2, 2, 8, 8, 3, 2, 3, 3, 4, 3, 3, 3, 3, 3, 3, 3, 3, 4, 4, 3, 1, 1, 6, 1, 1, 4, 3, 1, 1, 5, 5, 5, 5, 5, 1, 1, 1, 4, 4, 4, 1, 1, 5, 7, 1, 5, 5, 5, 1, 1, 4, 5, 5, 5, 5, 5, 5, 5, 5, 5, 5, 5, 5, 5, 5, 7, 1, 1, 1, 1, 6, 1, 1, 1, 1, 7, 7, 7, 7, 7, 7, 7, 7, 7, 7, 7, 4, 7, 7, 6, 7, 6, 7, 7, 7, 6, 4, 7, 7, 6, 7, 4, 6, 1, 6, 7, 6, 7, 6, 4, 6, 4, 6, 6, 7, 7, 7, 7, 6, 7, 7, 6, 4, 3, 6, 4, 4, 4, 4, 3, 3, 6, 6, 6, 6, 6, 6, 6, 6, 3, 3, 3, 6, 4, 4, 4, 4, 6, 6, 6, 6, 6, 4, 8, 2, 4, 4, 4, 4, 4, 4, 3, 4, 6, 6, 4, 4, 4, 4, 4, 4, 4, 4, 4, 4, 4, 4, 4, 2, 2, 2, 2, 2, 4, 2, 2, 2, 2, 2, 2, 2, 0, 0, 2, 0, 0, 0, 0, 0, 2, 0, 2, 0, 0, 2, 2, 2, 2, 2, 2, 2, 0, 0, 0, 0, 0, 0, 0, 2, 2, 2, 0, 0, 0, 0, 2, 2, 2, 2, 2, 2, 2, 2, 2, 2, 2, 2, 0, 2, 0, 0, 0, 0], "10": [1, 7, 7, 7, 7, 7, 7, 7, 7, 7, 7, 7, 7, 1, 7, 7, 1, 7, 7, 7, 7, 7, 7, 7, 7, 7, 1, 7, 7, 7, 7, 7, 7, 7, 7, 7, 7, 7, 1, 1, 1, 7, 7, 7, 2, 2, 2, 2, 2, 2, 2, 2, 1, 2, 2, 2, 2, 2, 2, 1, 1, 2, 1, 2, 2, 1, 1, 1, 8, 7, 2, 1, 1, 1, 6, 8, 2, 2, 2, 2, 2, 6, 6, 2, 2, 2, 2, 6, 6, 6, 6, 6, 2, 7, 2, 2, 2, 2, 2, 1, 1, 2, 2, 7, 2, 6, 6, 6, 6, 6, 6, 6, 0, 6, 6, 1, 2, 2, 2, 1, 6, 6, 8, 1, 2, 2, 6, 1, 6, 6, 8, 2, 6, 6, 6, 6, 6, 6, 6, 8, 8, 6, 9, 9, 6, 9, 9, 8, 6, 9, 9, 4, 4, 4, 4, 4, 3, 9, 9, 3, 8, 3, 9, 9, 4, 5, 9, 4, 4, 4, 3, 3, 3, 4, 4, 4, 4, 4, 4, 4, 4, 4, 4, 4, 4, 4, 3, 5, 9, 9, 9, 3, 0, 9, 9, 9, 9, 5, 5, 5, 5, 5, 5, 5, 5, 5, 5, 5, 8, 5, 5, 0, 5, 0, 5, 5, 5, 0, 0, 5, 5, 0, 5, 0, 0, 9, 0, 5, 0, 5, 0, 8, 0, 0, 0, 0, 5, 5, 5, 5, 0, 5, 5, 0, 8, 6, 0, 8, 8, 8, 8, 6, 6, 0, 0, 0, 0, 0, 0, 0, 0, 6, 6, 6, 0, 8, 8, 8, 8, 0, 0, 0, 0, 0, 8, 2, 1, 8, 8, 8, 8, 8, 8, 2, 8, 0, 0, 8, 8, 8, 8, 8, 8, 8, 8, 8, 8, 8, 8, 8, 8, 1, 1, 1, 8, 8, 8, 8, 1, 1, 1, 1, 1, 1, 1, 1, 1, 7, 1, 1, 1, 1, 7, 1, 1, 1, 1, 1, 1, 1, 1, 1, 1, 7, 7, 7, 7, 7, 7, 7, 1, 1, 1, 7, 7, 7, 7, 1, 8, 1, 1, 1, 1, 1, 1, 1, 1, 1, 1, 7, 1, 7, 7, 7, 7], "11": [9, 9, 10, 10, 10, 9, 9, 9, 9, 10, 10, 9, 9, 9, 9, 9, 9, 10, 10, 10, 10, 10, 10, 10, 10, 9, 9, 9, 10, 10, 10, 9, 9, 9, 10, 10, 10, 10, 9, 1, 1, 9, 9, 9, 6, 6, 6, 6, 6, 6, 6, 6, 1, 6, 6, 6, 6, 6, 5, 1, 1, 6, 1, 6, 6, 1, 1, 1, 5, 9, 6, 6, 9, 1, 0, 5, 6, 6, 6, 6, 6, 0, 0, 6, 6, 6, 6, 0, 0, 0, 0, 0, 0, 9, 6, 6, 0, 0, 5, 1, 1, 6, 6, 9, 6, 0, 0, 0, 0, 0, 0, 0, 2, 0, 0, 1, 6, 6, 6, 1, 0, 0, 1, 1, 6, 6, 0, 1, 0, 0, 5, 0, 0, 0, 0, 0, 0, 0, 0, 5, 5, 7, 7, 7, 2, 7, 7, 5, 0, 7, 7, 3, 3, 3, 3, 3, 8, 7, 7, 8, 5, 8, 7, 7, 3, 4, 7, 3, 3, 3, 8, 8, 8, 3, 3, 3, 3, 3, 3, 3, 3, 3, 3, 3, 3, 3, 3, 4, 8, 7, 7, 8, 2, 7, 7, 7, 7, 7, 4, 4, 4, 4, 4, 3, 4, 4, 4, 4, 2, 4, 4, 4, 4, 2, 4, 4, 4, 2, 2, 4, 4, 2, 4, 2, 2, 7, 2, 4, 2, 4, 2, 5, 2, 2, 2, 2, 4, 4, 4, 4, 4, 4, 4, 2, 5, 0, 2, 5, 5, 2, 5, 0, 0, 2, 2, 2, 2, 2, 4, 2, 2, 0, 0, 0, 2, 5, 5, 5, 5, 2, 2, 2, 2, 2, 5, 6, 1, 5, 5, 5, 5, 5, 5, 0, 2, 2, 2, 5, 5, 5, 5, 5, 5, 5, 5, 5, 5, 5, 5, 5, 5, 1, 1, 1, 1, 5, 5, 5, 1, 1, 1, 9, 9, 9, 9, 1, 9, 9, 9, 9, 9, 9, 9, 9, 9, 9, 1, 1, 1, 1, 1, 1, 1, 9, 9, 9, 10, 10, 10, 9, 1, 1, 1, 9, 10, 9, 9, 1, 5, 1, 1, 1, 1, 1, 1, 1, 1, 1, 1, 9, 1, 9, 10, 10, 10], "12": [7, 7, 2, 2, 2, 7, 7, 7, 7, 2, 2, 7, 7, 7, 7, 7, 7, 2, 2, 2, 2, 2, 2, 2, 2, 7, 7, 7, 2, 2, 2, 7, 7, 7, 2, 2, 2, 2, 7, 0, 0, 7, 7, 7, 5, 5, 5, 5, 5, 5, 5, 5, 0, 5, 5, 5, 5, 5, 6, 0, 0, 5, 0, 5, 5, 0, 0, 0, 0, 7, 5, 5, 7, 0, 6, 0, 5, 5, 5, 5, 5, 6, 6, 5, 5, 5, 5, 6, 6, 6, 6, 6, 6, 7, 5, 5, 6, 6, 0, 0, 0, 5, 5, 7, 5, 6, 6, 6, 6, 6, 6, 6, 4, 6, 6, 0, 5, 5, 5, 0, 6, 10, 0, 0, 5, 10, 10, 0, 10, 6, 9, 10, 10, 10, 10, 10, 10, 6, 6, 9, 9, 8, 8, 8, 4, 8, 8, 9, 10, 8, 8, 3, 3, 3, 3, 11, 8, 8, 8, 9, 9, 9, 8, 3, 3, 1, 8, 3, 3, 3, 8, 8, 4, 3, 3, 3, 3, 3, 3, 3, 3, 11, 11, 3, 3, 3, 3, 1, 8, 8, 8, 8, 4, 8, 8, 8, 11, 11, 11, 11, 11, 11, 11, 11, 11, 11, 11, 1, 4, 1, 11, 1, 1, 4, 1, 1, 1, 4, 4, 1, 1, 4, 1, 4, 4, 1, 4, 1, 4, 1, 4, 9, 6, 4, 4, 1, 1, 1, 1, 1, 1, 1, 1, 4, 9, 6, 1, 9, 9, 9, 9, 6, 6, 6, 1, 1, 4, 1, 1, 4, 4, 6, 6, 6, 4, 9, 9, 9, 9, 4, 4, 4, 4, 6, 9, 5, 0, 9, 9, 9, 9, 9, 9, 6, 9, 4, 4, 9, 9, 9, 9, 9, 9, 9, 9, 9, 9, 9, 9, 9, 0, 0, 0, 0, 0, 9, 0, 9, 0, 0, 0, 7, 7, 7, 7, 0, 7, 7, 7, 7, 7, 7, 7, 7, 7, 7, 0, 0, 0, 0, 0, 0, 0, 7, 7, 7, 2, 2, 2, 7, 0, 0, 0, 7, 2, 7, 7, 0, 0, 0, 0, 0, 0, 0, 0, 0, 0, 0, 0, 7, 0, 7, 2, 2, 2], "13": [6, 6, 12, 12, 12, 6, 6, 6, 12, 12, 12, 12, 6, 6, 6, 12, 6, 12, 12, 12, 12, 12, 12, 12, 12, 6, 6, 12, 12, 12, 12, 6, 6, 12, 12, 12, 12, 12, 2, 0, 0, 6, 6, 2, 2, 2, 2, 5, 5, 5, 5, 5, 0, 2, 2, 5, 5, 5, 5, 0, 0, 5, 0, 5, 5, 0, 0, 0, 0, 6, 5, 2, 6, 0, 3, 0, 2, 2, 5, 5, 5, 3, 3, 5, 2, 5, 5, 3, 3, 3, 3, 3, 3, 6, 2, 5, 3, 5, 0, 0, 0, 5, 2, 6, 5, 3, 3, 3, 3, 10, 7, 7, 7, 3, 3, 0, 5, 5, 5, 0, 3, 3, 0, 0, 2, 5, 3, 0, 3, 3, 9, 3, 3, 3, 3, 3, 3, 3, 3, 9, 9, 10, 10, 10, 7, 10, 10, 9, 3, 10, 10, 4, 4, 4, 4, 8, 11, 10, 10, 11, 9, 11, 10, 4, 4, 1, 10, 4, 4, 4, 11, 11, 11, 4, 4, 4, 4, 4, 4, 4, 4, 8, 8, 4, 4, 4, 4, 1, 11, 10, 10, 11, 7, 10, 10, 10, 8, 8, 8, 8, 8, 1, 8, 8, 8, 8, 8, 1, 9, 1, 8, 1, 1, 7, 1, 1, 1, 7, 7, 1, 1, 7, 1, 9, 7, 10, 7, 1, 7, 1, 7, 9, 7, 7, 7, 1, 1, 1, 1, 1, 1, 1, 1, 7, 9, 3, 1, 9, 9, 9, 9, 3, 3, 7, 7, 7, 7, 7, 1, 7, 7, 3, 3, 3, 7, 9, 9, 9, 9, 7, 7, 7, 7, 7, 9, 5, 0, 9, 9, 9, 9, 9, 9, 5, 7, 7, 7, 9, 9, 9, 9, 9, 9, 9, 9, 9, 9, 9, 9, 9, 0, 0, 0, 0, 0, 9, 0, 0, 0, 0, 0, 6, 6, 6, 6, 6, 6, 6, 6, 6, 6, 6, 6, 6, 6, 6, 6, 0, 0, 0, 0, 0, 0, 6, 6, 6, 12, 12, 12, 6, 0, 0, 0, 6, 12, 6, 6, 0, 0, 0, 0, 0, 0, 0, 6, 0, 6, 0, 0, 6, 0, 6, 12, 12, 12], "14": [5, 5, 13, 13, 13, 5, 5, 5, 5, 13, 13, 5, 5, 5, 5, 5, 5, 13, 13, 13, 13, 13, 13, 13, 13, 5, 5, 5, 13, 13, 13, 5, 5, 5, 13, 13, 13, 13, 5, 1, 1, 5, 5, 5, 11, 11, 11, 11, 11, 11, 11, 11, 1, 11, 11, 11, 11, 11, 3, 1, 1, 3, 1, 11, 11, 1, 1, 1, 1, 5, 11, 11, 5, 1, 3, 1, 11, 11, 11, 11, 3, 3, 3, 11, 11, 11, 3, 3, 3, 3, 3, 3, 3, 5, 11, 3, 3, 3, 1, 1, 1, 11, 11, 5, 3, 3, 3, 12, 12, 12, 12, 12, 12, 12, 9, 1, 11, 11, 11, 1, 3, 9, 1, 1, 11, 9, 9, 1, 9, 3, 2, 9, 9, 9, 9, 9, 9, 12, 12, 2, 2, 12, 10, 10, 12, 10, 10, 2, 9, 10, 10, 4, 4, 4, 4, 7, 8, 12, 10, 8, 2, 8, 12, 10, 4, 0, 10, 10, 4, 4, 8, 8, 8, 4, 4, 4, 4, 4, 4, 4, 4, 7, 10, 4, 4, 4, 10, 0, 8, 10, 10, 8, 6, 10, 10, 10, 10, 10, 0, 7, 7, 0, 7, 7, 7, 7, 7, 0, 2, 0, 0, 6, 0, 6, 0, 0, 0, 6, 6, 0, 0, 6, 0, 2, 12, 12, 12, 0, 6, 0, 6, 2, 12, 2, 6, 6, 0, 0, 0, 0, 6, 0, 0, 6, 2, 12, 12, 2, 2, 2, 2, 3, 12, 12, 12, 12, 6, 6, 0, 6, 2, 3, 3, 3, 6, 2, 2, 2, 2, 6, 2, 12, 2, 12, 2, 11, 1, 2, 2, 2, 2, 2, 2, 3, 2, 6, 2, 2, 3, 2, 2, 2, 2, 2, 2, 2, 2, 2, 2, 2, 1, 1, 1, 1, 1, 2, 1, 1, 1, 1, 1, 5, 5, 5, 5, 1, 5, 5, 5, 5, 5, 5, 5, 5, 5, 5, 1, 1, 1, 1, 1, 1, 1, 5, 5, 5, 13, 13, 13, 5, 1, 1, 1, 5, 13, 5, 5, 1, 1, 1, 1, 1, 1, 1, 1, 1, 1, 1, 1, 5, 1, 5, 13, 13, 13], "15": [5, 5, 0, 0, 0, 5, 5, 5, 0, 0, 0, 0, 5, 5, 5, 0, 5, 0, 0, 0, 0, 0, 0, 0, 0, 5, 5, 0, 0, 0, 0, 5, 5, 0, 0, 0, 0, 0, 5, 8, 8, 5, 5, 0, 6, 6, 6, 6, 6, 6, 6, 6, 8, 6, 6, 6, 6, 6, 1, 8, 8, 6, 8, 6, 6, 8, 8, 8, 8, 5, 6, 5, 5, 8, 1, 8, 6, 6, 6, 6, 1, 1, 1, 6, 6, 6, 1, 1, 1, 1, 1, 1, 1, 5, 6, 6, 1, 1, 8, 8, 8, 6, 6, 5, 6, 1, 1, 1, 14, 14, 14, 14, 14, 14, 9, 8, 6, 6, 6, 8, 1, 9, 8, 8, 6, 9, 9, 8, 9, 1, 13, 9, 9, 9, 9, 9, 9, 14, 1, 13, 13, 10, 10, 10, 12, 10, 10, 13, 9, 10, 10, 3, 3, 3, 3, 11, 12, 10, 10, 12, 13, 12, 10, 3, 3, 7, 2, 3, 3, 3, 2, 2, 12, 3, 3, 3, 3, 3, 3, 3, 3, 11, 3, 3, 3, 3, 2, 7, 2, 10, 10, 2, 14, 10, 10, 2, 10, 11, 11, 11, 11, 11, 11, 11, 11, 11, 11, 7, 4, 7, 11, 14, 7, 14, 7, 7, 7, 4, 4, 7, 11, 4, 7, 4, 14, 14, 14, 7, 4, 7, 4, 13, 14, 4, 14, 14, 7, 7, 7, 7, 7, 7, 7, 4, 4, 14, 14, 13, 13, 13, 13, 1, 1, 14, 14, 14, 14, 14, 7, 14, 1, 1, 1, 1, 4, 13, 13, 4, 4, 4, 4, 14, 4, 14, 13, 6, 8, 13, 13, 13, 13, 13, 13, 1, 13, 4, 4, 13, 13, 13, 13, 13, 13, 13, 13, 13, 13, 13, 13, 13, 8, 8, 8, 8, 8, 13, 8, 13, 8, 8, 8, 5, 5, 5, 5, 5, 5, 5, 5, 5, 5, 5, 5, 5, 5, 5, 5, 8, 8, 8, 8, 8, 8, 5, 5, 5, 0, 0, 0, 5, 8, 8, 8, 5, 0, 5, 5, 8, 8, 8, 8, 8, 8, 8, 5, 8, 5, 8, 8, 5, 8, 5, 0, 0, 0], "16": [8, 8, 3, 3, 3, 8, 8, 8, 3, 3, 3, 3, 8, 8, 8, 3, 8, 3, 3, 3, 3, 3, 3, 3, 3, 8, 8, 3, 3, 3, 3, 8, 8, 3, 3, 3, 3, 3, 8, 5, 5, 8, 8, 3, 1, 1, 1, 1, 1, 1, 1, 1, 5, 1, 1, 1, 1, 1, 12, 5, 5, 12, 5, 1, 1, 5, 5, 5, 12, 8, 1, 8, 8, 5, 7, 12, 1, 1, 1, 1, 1, 7, 7, 1, 1, 1, 1, 7, 7, 7, 7, 7, 7, 8, 1, 1, 7, 7, 12, 5, 5, 1, 1, 8, 1, 7, 7, 7, 7, 7, 7, 7, 9, 7, 7, 5, 1, 1, 1, 5, 7, 7, 12, 5, 1, 1, 10, 5, 10, 7, 12, 7, 10, 10, 10, 10, 10, 7, 7, 12, 12, 2, 2, 2, 11, 2, 2, 12, 7, 2, 2, 6, 6, 6, 6, 14, 11, 2, 2, 11, 0, 11, 15, 6, 6, 4, 15, 6, 6, 13, 15, 6, 11, 6, 6, 13, 13, 13, 13, 13, 13, 13, 14, 6, 6, 13, 6, 4, 15, 2, 2, 15, 9, 2, 2, 15, 2, 14, 4, 14, 14, 14, 14, 14, 14, 14, 14, 4, 0, 4, 14, 9, 4, 9, 4, 4, 4, 9, 0, 4, 4, 9, 4, 0, 9, 2, 9, 4, 9, 4, 9, 0, 9, 0, 9, 9, 4, 4, 4, 4, 9, 4, 4, 9, 0, 7, 9, 0, 12, 0, 12, 7, 7, 7, 9, 9, 9, 9, 9, 9, 0, 7, 7, 7, 9, 0, 12, 0, 0, 9, 0, 9, 0, 7, 12, 1, 5, 12, 12, 12, 0, 12, 12, 7, 0, 0, 0, 12, 12, 12, 12, 12, 12, 0, 12, 12, 0, 0, 12, 0, 12, 5, 5, 5, 12, 12, 12, 12, 5, 5, 5, 8, 8, 8, 8, 5, 8, 8, 8, 8, 8, 8, 8, 8, 8, 8, 5, 5, 5, 5, 5, 5, 5, 8, 8, 8, 3, 3, 3, 8, 5, 5, 5, 8, 3, 8, 8, 5, 12, 5, 5, 5, 5, 5, 5, 5, 5, 5, 5, 8, 5, 8, 3, 3, 3], "17": [2, 2, 7, 7, 2, 2, 2, 2, 2, 7, 7, 2, 2, 2, 2, 2, 10, 7, 7, 7, 7, 7, 7, 7, 7, 2, 2, 2, 7, 7, 7, 2, 2, 2, 7, 7, 7, 7, 13, 10, 10, 2, 2, 13, 13, 13, 13, 13, 13, 4, 13, 4, 16, 13, 13, 13, 4, 4, 4, 10, 10, 4, 16, 13, 13, 16, 10, 16, 16, 2, 13, 13, 2, 10, 12, 16, 13, 13, 13, 4, 4, 12, 12, 4, 13, 13, 4, 12, 12, 12, 12, 12, 4, 2, 13, 4, 4, 4, 16, 16, 16, 4, 13, 2, 4, 12, 12, 8, 8, 8, 8, 8, 8, 8, 9, 10, 4, 4, 4, 16, 12, 9, 16, 10, 13, 4, 9, 16, 9, 12, 16, 4, 9, 9, 9, 9, 9, 9, 8, 16, 16, 14, 11, 11, 0, 14, 11, 0, 9, 14, 14, 5, 5, 5, 5, 1, 6, 14, 14, 6, 0, 6, 14, 11, 5, 11, 14, 5, 5, 5, 6, 6, 6, 5, 5, 5, 5, 5, 5, 5, 5, 1, 1, 5, 5, 5, 5, 15, 14, 14, 11, 6, 3, 11, 11, 14, 11, 1, 15, 1, 1, 15, 1, 1, 1, 1, 1, 15, 0, 15, 15, 15, 15, 3, 15, 15, 15, 3, 3, 15, 15, 3, 15, 3, 8, 8, 3, 15, 3, 15, 3, 0, 8, 3, 3, 3, 15, 15, 15, 15, 15, 15, 15, 3, 0, 8, 8, 0, 0, 0, 16, 12, 8, 8, 8, 8, 3, 3, 15, 3, 0, 12, 12, 12, 3, 0, 0, 0, 0, 3, 0, 8, 0, 8, 0, 4, 16, 16, 16, 0, 0, 16, 0, 12, 0, 3, 0, 16, 0, 0, 0, 0, 0, 0, 0, 0, 0, 0, 16, 0, 16, 10, 10, 10, 16, 0, 16, 16, 16, 10, 10, 2, 10, 2, 2, 10, 2, 2, 2, 2, 2, 10, 2, 10, 2, 2, 10, 10, 10, 10, 10, 16, 10, 2, 2, 2, 7, 7, 7, 2, 16, 16, 10, 2, 7, 2, 2, 10, 16, 10, 10, 16, 10, 10, 10, 10, 10, 10, 10, 2, 10, 2, 7, 7, 7], "18": [4, 4, 6, 6, 6, 4, 4, 4, 6, 6, 6, 6, 4, 4, 4, 6, 4, 6, 6, 6, 6, 6, 6, 6, 6, 4, 4, 6, 6, 6, 6, 4, 4, 6, 6, 6, 6, 6, 1, 3, 3, 4, 4, 1, 1, 1, 1, 1, 1, 9, 1, 1, 3, 1, 1, 1, 1, 9, 9, 3, 3, 9, 3, 1, 1, 3, 3, 3, 3, 4, 1, 1, 4, 3, 7, 3, 1, 1, 1, 1, 7, 7, 7, 1, 1, 1, 7, 7, 7, 7, 7, 7, 7, 4, 1, 7, 7, 9, 3, 3, 3, 1, 1, 4, 7, 7, 7, 11, 11, 11, 11, 11, 11, 11, 11, 3, 1, 1, 1, 3, 7, 17, 3, 3, 1, 17, 17, 3, 17, 7, 12, 7, 17, 17, 17, 17, 17, 14, 11, 12, 12, 11, 2, 2, 14, 2, 2, 12, 14, 2, 2, 16, 16, 16, 16, 13, 14, 11, 2, 14, 12, 14, 10, 16, 16, 5, 10, 16, 16, 8, 10, 16, 15, 16, 16, 8, 8, 8, 8, 8, 8, 13, 13, 16, 16, 8, 16, 5, 10, 2, 2, 10, 10, 2, 2, 10, 2, 13, 5, 13, 13, 5, 13, 13, 13, 13, 13, 5, 15, 5, 5, 10, 5, 15, 5, 5, 5, 15, 15, 5, 5, 15, 5, 15, 11, 11, 0, 5, 0, 5, 0, 12, 11, 15, 0, 0, 5, 5, 5, 5, 5, 5, 5, 15, 12, 11, 11, 12, 12, 0, 12, 7, 11, 0, 0, 0, 0, 0, 5, 0, 0, 7, 7, 7, 0, 12, 12, 12, 12, 0, 0, 0, 0, 0, 12, 1, 3, 12, 12, 9, 9, 12, 12, 9, 9, 0, 0, 12, 9, 9, 12, 12, 12, 12, 12, 12, 12, 12, 9, 9, 12, 3, 3, 3, 3, 12, 12, 12, 3, 3, 3, 4, 4, 4, 4, 4, 4, 4, 4, 4, 4, 4, 4, 4, 4, 4, 4, 3, 3, 3, 3, 3, 3, 4, 4, 4, 6, 6, 6, 4, 3, 3, 3, 4, 6, 4, 4, 3, 3, 3, 3, 3, 3, 3, 4, 3, 4, 3, 3, 4, 3, 4, 6, 6, 6], "19": [0, 0, 7, 7, 7, 0, 0, 0, 7, 7, 7, 7, 0, 0, 0, 7, 0, 7, 7, 7, 7, 7, 7, 7, 7, 0, 0, 7, 7, 7, 7, 0, 0, 7, 7, 7, 7, 7, 5, 15, 15, 0, 0, 5, 5, 5, 5, 5, 5, 16, 16, 16, 10, 5, 5, 5, 16, 16, 6, 15, 15, 16, 10, 16, 16, 10, 15, 10, 10, 0, 5, 5, 0, 15, 6, 10, 5, 5, 5, 16, 6, 6, 6, 16, 5, 5, 6, 6, 6, 6, 6, 6, 16, 0, 5, 16, 6, 6, 10, 10, 10, 16, 16, 0, 6, 6, 6, 1, 1, 1, 1, 1, 1, 1, 1, 10, 16, 16, 16, 10, 6, 17, 10, 16, 5, 16, 17, 10, 17, 6, 3, 16, 17, 17, 17, 17, 17, 1, 1, 3, 3, 1, 9, 9, 14, 9, 9, 3, 17, 9, 9, 2, 2, 2, 2, 18, 12, 1, 9, 12, 3, 12, 13, 11, 11, 8, 13, 11, 2, 2, 12, 11, 12, 2, 2, 2, 2, 2, 2, 2, 2, 18, 18, 2, 2, 2, 11, 8, 13, 9, 9, 12, 13, 9, 9, 13, 9, 18, 8, 18, 18, 13, 18, 18, 18, 18, 18, 8, 4, 8, 18, 13, 8, 4, 8, 8, 8, 4, 4, 8, 8, 4, 8, 4, 1, 1, 1, 8, 4, 8, 4, 3, 1, 4, 4, 4, 8, 8, 8, 8, 4, 8, 8, 4, 3, 1, 1, 3, 3, 14, 3, 6, 1, 1, 1, 1, 4, 4, 8, 4, 14, 6, 6, 6, 14, 3, 3, 14, 14, 4, 14, 14, 14, 14, 3, 16, 10, 3, 10, 14, 14, 3, 3, 6, 14, 14, 14, 3, 14, 14, 3, 3, 3, 3, 3, 3, 3, 3, 10, 14, 3, 15, 15, 15, 10, 3, 10, 10, 10, 15, 15, 0, 0, 0, 0, 15, 0, 0, 0, 0, 0, 0, 0, 0, 0, 0, 15, 15, 15, 15, 10, 10, 15, 0, 0, 0, 7, 7, 7, 0, 10, 10, 15, 0, 7, 0, 0, 15, 10, 15, 15, 10, 15, 15, 15, 15, 15, 15, 15, 0, 15, 0, 7, 7, 7], "20": [2, 12, 6, 6, 12, 12, 12, 12, 12, 6, 6, 12, 2, 2, 12, 12, 2, 6, 6, 6, 6, 6, 6, 6, 6, 12, 2, 12, 12, 12, 6, 12, 12, 12, 6, 6, 6, 6, 18, 5, 5, 12, 12, 18, 18, 18, 18, 18, 18, 11, 11, 11, 5, 18, 18, 18, 11, 11, 11, 5, 5, 11, 5, 11, 11, 5, 5, 5, 5, 12, 18, 18, 2, 5, 7, 5, 18, 18, 18, 7, 7, 7, 7, 11, 18, 18, 7, 7, 7, 7, 7, 7, 11, 12, 18, 7, 7, 11, 11, 5, 5, 11, 18, 12, 7, 7, 7, 3, 3, 3, 3, 3, 3, 3, 3, 5, 11, 11, 11, 5, 7, 16, 5, 5, 18, 16, 16, 5, 16, 7, 10, 16, 16, 16, 16, 16, 16, 3, 3, 10, 10, 3, 9, 9, 1, 9, 9, 10, 16, 9, 17, 0, 8, 0, 8, 8, 19, 3, 17, 14, 10, 14, 17, 9, 0, 4, 17, 9, 0, 8, 19, 9, 19, 0, 0, 8, 8, 8, 8, 8, 8, 8, 8, 0, 0, 8, 8, 4, 17, 17, 9, 19, 17, 9, 9, 17, 9, 15, 15, 15, 15, 15, 15, 15, 15, 15, 15, 4, 13, 4, 15, 17, 4, 13, 4, 4, 4, 13, 13, 4, 15, 13, 4, 13, 3, 3, 3, 4, 13, 4, 13, 10, 3, 13, 13, 4, 4, 4, 4, 4, 4, 4, 4, 13, 10, 3, 3, 10, 10, 1, 10, 7, 3, 3, 3, 3, 1, 4, 4, 1, 1, 7, 7, 7, 1, 10, 10, 1, 1, 1, 1, 1, 1, 1, 10, 11, 5, 10, 10, 11, 1, 10, 10, 11, 1, 1, 1, 10, 11, 1, 10, 10, 10, 10, 10, 10, 10, 10, 10, 1, 10, 5, 2, 2, 5, 10, 10, 10, 5, 5, 2, 2, 2, 2, 2, 2, 2, 12, 2, 2, 2, 2, 12, 2, 2, 2, 2, 5, 2, 5, 5, 5, 5, 12, 12, 12, 12, 6, 12, 12, 5, 5, 5, 12, 6, 12, 12, 5, 5, 2, 2, 5, 2, 2, 2, 2, 2, 2, 2, 12, 2, 12, 6, 6, 6], "21": [2, 2, 14, 14, 14, 2, 2, 2, 2, 14, 14, 2, 2, 2, 2, 2, 2, 14, 14, 14, 14, 14, 14, 14, 14, 2, 2, 2, 14, 14, 14, 2, 2, 2, 14, 14, 14, 14, 0, 11, 11, 2, 2, 0, 0, 0, 0, 0, 0, 17, 0, 0, 17, 0, 0, 0, 0, 8, 8, 11, 11, 8, 17, 0, 0, 17, 11, 17, 17, 2, 0, 0, 2, 11, 8, 17, 0, 0, 16, 16, 16, 8, 8, 0, 0, 16, 16, 8, 8, 8, 8, 8, 8, 2, 0, 16, 8, 8, 17, 11, 17, 16, 0, 2, 16, 8, 8, 6, 6, 6, 6, 6, 6, 6, 6, 17, 17, 16, 0, 17, 9, 9, 17, 17, 0, 16, 9, 17, 9, 8, 17, 16, 9, 9, 9, 9, 9, 6, 6, 15, 15, 6, 5, 5, 20, 5, 5, 15, 9, 5, 5, 7, 19, 7, 19, 19, 20, 6, 5, 20, 4, 20, 3, 13, 13, 18, 3, 13, 7, 19, 3, 13, 20, 13, 7, 19, 19, 19, 19, 19, 19, 19, 19, 7, 7, 19, 13, 18, 3, 5, 5, 3, 10, 5, 5, 3, 5, 1, 18, 1, 1, 18, 1, 1, 1, 1, 1, 12, 4, 18, 18, 18, 18, 10, 18, 18, 12, 10, 4, 18, 12, 10, 12, 4, 6, 6, 6, 18, 10, 12, 10, 15, 6, 4, 10, 10, 12, 12, 12, 12, 10, 12, 12, 10, 4, 6, 6, 15, 15, 4, 15, 8, 6, 6, 6, 6, 10, 10, 12, 10, 4, 8, 8, 8, 4, 4, 15, 4, 4, 10, 4, 6, 4, 8, 15, 16, 11, 15, 15, 8, 4, 15, 15, 8, 4, 4, 4, 15, 8, 8, 15, 15, 15, 15, 15, 15, 15, 4, 15, 4, 15, 11, 11, 11, 15, 15, 15, 15, 17, 11, 11, 2, 2, 2, 2, 11, 2, 2, 2, 2, 2, 2, 2, 2, 2, 2, 11, 11, 11, 11, 11, 11, 11, 2, 2, 2, 14, 14, 14, 2, 11, 11, 11, 2, 14, 2, 2, 11, 15, 11, 11, 11, 11, 11, 11, 11, 11, 11, 11, 2, 11, 2, 14, 14, 14], "22": [4, 4, 11, 11, 11, 4, 4, 4, 11, 11, 11, 4, 4, 4, 4, 4, 4, 11, 11, 11, 11, 11, 11, 11, 11, 4, 4, 11, 11, 11, 11, 4, 4, 11, 11, 11, 11, 11, 13, 1, 1, 4, 4, 13, 13, 13, 13, 13, 13, 19, 13, 8, 1, 13, 13, 8, 8, 8, 10, 1, 1, 10, 6, 13, 13, 19, 1, 6, 6, 4, 8, 13, 4, 1, 0, 19, 13, 13, 8, 8, 8, 0, 0, 13, 13, 13, 8, 0, 0, 0, 0, 0, 0, 4, 13, 8, 0, 0, 19, 1, 19, 8, 13, 4, 8, 0, 0, 9, 9, 9, 9, 9, 3, 9, 9, 19, 19, 8, 13, 19, 0, 17, 19, 19, 13, 17, 17, 19, 17, 0, 19, 17, 17, 17, 17, 17, 9, 9, 0, 6, 6, 9, 14, 14, 10, 14, 14, 19, 17, 14, 14, 7, 7, 7, 7, 2, 20, 9, 14, 21, 12, 21, 5, 7, 7, 16, 5, 7, 15, 15, 21, 21, 18, 7, 15, 15, 15, 15, 15, 15, 15, 2, 15, 15, 15, 15, 20, 16, 20, 14, 14, 20, 5, 14, 14, 5, 14, 14, 16, 2, 2, 16, 2, 2, 2, 2, 2, 16, 18, 16, 16, 5, 16, 18, 16, 16, 16, 18, 18, 16, 16, 18, 16, 18, 3, 9, 3, 16, 3, 16, 3, 12, 3, 18, 3, 3, 16, 16, 16, 16, 3, 16, 16, 18, 12, 9, 9, 12, 12, 10, 6, 0, 0, 3, 3, 3, 3, 3, 3, 3, 10, 0, 0, 0, 3, 12, 12, 12, 12, 3, 10, 3, 10, 10, 12, 8, 6, 6, 6, 10, 12, 6, 6, 10, 10, 3, 10, 6, 10, 10, 12, 12, 12, 12, 12, 12, 12, 12, 6, 10, 6, 1, 1, 1, 6, 12, 6, 6, 6, 1, 1, 4, 4, 4, 4, 1, 4, 4, 4, 4, 4, 4, 4, 4, 4, 4, 1, 1, 1, 1, 1, 6, 1, 4, 4, 4, 11, 11, 11, 4, 1, 1, 1, 4, 11, 4, 4, 1, 6, 1, 1, 6, 1, 1, 1, 1, 1, 1, 1, 4, 1, 4, 11, 11, 11], "23": [16, 4, 15, 15, 4, 4, 4, 4, 4, 15, 15, 4, 4, 16, 4, 4, 16, 15, 15, 15, 15, 15, 15, 15, 15, 4, 16, 4, 15, 15, 15, 4, 4, 4, 15, 15, 15, 15, 16, 1, 1, 4, 16, 5, 5, 5, 5, 5, 5, 14, 5, 5, 1, 5, 5, 5, 5, 5, 18, 1, 1, 18, 1, 5, 5, 1, 1, 1, 6, 16, 5, 16, 16, 1, 18, 14, 16, 5, 5, 5, 18, 18, 18, 14, 5, 5, 18, 18, 18, 18, 18, 18, 14, 4, 5, 5, 18, 18, 14, 1, 1, 14, 5, 4, 5, 18, 0, 13, 13, 13, 13, 13, 13, 13, 13, 1, 14, 5, 14, 14, 0, 7, 14, 14, 5, 14, 7, 1, 7, 0, 14, 14, 7, 7, 7, 7, 7, 0, 0, 6, 6, 0, 10, 10, 9, 10, 17, 6, 7, 10, 10, 3, 19, 3, 19, 19, 22, 0, 10, 22, 6, 22, 20, 3, 3, 11, 20, 3, 3, 19, 17, 17, 21, 3, 12, 12, 12, 12, 12, 12, 12, 8, 19, 3, 3, 19, 3, 11, 17, 10, 10, 17, 20, 17, 11, 20, 19, 19, 11, 11, 8, 11, 8, 8, 8, 8, 8, 2, 21, 11, 11, 20, 11, 20, 11, 11, 2, 21, 21, 11, 2, 21, 2, 21, 13, 13, 9, 11, 21, 2, 21, 6, 13, 21, 9, 2, 2, 2, 2, 2, 2, 2, 2, 21, 6, 13, 13, 6, 6, 9, 6, 18, 13, 13, 13, 13, 9, 2, 2, 9, 9, 18, 18, 18, 9, 6, 6, 9, 9, 9, 9, 9, 9, 9, 6, 5, 1, 6, 6, 14, 6, 6, 6, 18, 9, 9, 9, 6, 18, 18, 6, 6, 6, 6, 6, 6, 6, 6, 6, 9, 6, 1, 1, 1, 1, 6, 6, 6, 1, 1, 1, 16, 16, 16, 16, 16, 16, 16, 16, 16, 16, 16, 16, 16, 16, 16, 1, 1, 1, 1, 1, 1, 1, 16, 4, 4, 15, 15, 4, 16, 1, 1, 1, 4, 15, 4, 4, 1, 6, 1, 1, 1, 1, 1, 16, 1, 1, 1, 1, 4, 1, 4, 15, 15, 15], "24": [18, 11, 0, 0, 11, 11, 11, 11, 11, 0, 0, 11, 18, 18, 11, 11, 18, 0, 0, 0, 0, 0, 0, 0, 0, 11, 18, 11, 0, 0, 0, 11, 11, 11, 0, 0, 0, 0, 7, 5, 5, 11, 11, 7, 7, 7, 7, 22, 22, 22, 22, 22, 5, 7, 7, 22, 22, 22, 22, 5, 5, 22, 5, 22, 22, 2, 5, 5, 8, 11, 23, 7, 18, 5, 14, 5, 7, 7, 23, 23, 23, 14, 14, 2, 7, 23, 23, 14, 14, 14, 14, 14, 14, 11, 7, 23, 14, 22, 2, 5, 5, 23, 7, 11, 22, 14, 14, 6, 6, 6, 6, 6, 21, 6, 6, 2, 2, 23, 22, 2, 14, 10, 2, 5, 7, 23, 10, 5, 10, 14, 2, 10, 10, 10, 10, 10, 10, 6, 6, 8, 8, 4, 4, 17, 6, 4, 4, 20, 10, 4, 4, 3, 17, 3, 17, 15, 16, 4, 4, 16, 20, 16, 4, 17, 17, 12, 4, 17, 3, 17, 19, 17, 1, 17, 3, 3, 3, 3, 3, 3, 3, 15, 17, 3, 3, 3, 17, 9, 4, 4, 17, 19, 21, 4, 12, 4, 17, 17, 12, 15, 15, 9, 15, 15, 15, 15, 15, 9, 1, 12, 12, 21, 12, 1, 12, 12, 9, 1, 1, 12, 9, 1, 12, 1, 21, 12, 21, 12, 1, 9, 1, 20, 6, 1, 21, 21, 12, 9, 9, 9, 9, 9, 9, 1, 20, 6, 21, 20, 20, 13, 8, 14, 6, 6, 21, 21, 21, 21, 9, 21, 13, 14, 14, 14, 13, 20, 20, 13, 13, 1, 13, 21, 13, 13, 20, 22, 8, 20, 8, 20, 13, 8, 20, 14, 13, 13, 13, 20, 13, 13, 20, 20, 20, 20, 20, 20, 20, 20, 20, 13, 8, 5, 5, 5, 8, 20, 8, 8, 5, 5, 18, 18, 18, 18, 18, 18, 18, 11, 18, 18, 18, 18, 11, 18, 18, 18, 18, 5, 18, 5, 5, 8, 5, 11, 11, 11, 0, 0, 11, 11, 5, 5, 5, 11, 0, 11, 11, 5, 8, 18, 5, 8, 18, 18, 18, 18, 18, 18, 5, 11, 18, 11, 0, 0, 0], "25": [6, 6, 8, 8, 6, 6, 6, 6, 6, 8, 8, 6, 6, 6, 6, 6, 9, 8, 8, 8, 8, 8, 8, 8, 8, 6, 6, 6, 8, 8, 8, 6, 6, 6, 8, 8, 8, 8, 14, 1, 9, 6, 6, 14, 14, 14, 14, 14, 14, 1, 14, 14, 1, 14, 14, 14, 14, 4, 20, 9, 1, 1, 5, 14, 14, 1, 1, 1, 5, 6, 14, 14, 6, 1, 20, 5, 14, 14, 14, 4, 4, 4, 20, 14, 14, 14, 4, 4, 4, 20, 20, 20, 16, 6, 14, 4, 20, 20, 1, 1, 1, 14, 14, 6, 4, 20, 20, 13, 13, 13, 13, 13, 15, 13, 13, 1, 16, 14, 14, 1, 4, 16, 1, 16, 14, 16, 21, 5, 16, 20, 16, 16, 21, 21, 16, 21, 13, 13, 13, 5, 5, 13, 10, 10, 2, 10, 10, 18, 16, 10, 10, 0, 0, 22, 0, 11, 7, 13, 10, 7, 18, 7, 19, 10, 22, 3, 19, 0, 0, 0, 19, 22, 12, 0, 24, 24, 24, 24, 24, 24, 24, 11, 0, 0, 0, 0, 22, 17, 19, 10, 10, 7, 19, 10, 3, 19, 10, 3, 3, 11, 11, 19, 11, 11, 11, 11, 11, 17, 18, 3, 3, 19, 3, 12, 3, 3, 17, 12, 12, 3, 17, 12, 17, 12, 15, 13, 15, 3, 15, 17, 2, 18, 15, 12, 15, 15, 17, 17, 17, 17, 17, 17, 17, 12, 18, 13, 15, 18, 23, 2, 5, 20, 20, 15, 15, 15, 15, 15, 17, 15, 2, 20, 20, 20, 15, 23, 23, 2, 23, 2, 2, 15, 2, 2, 5, 14, 5, 5, 5, 23, 23, 5, 23, 20, 2, 2, 2, 23, 20, 23, 23, 23, 23, 23, 23, 23, 23, 23, 23, 23, 5, 9, 9, 9, 5, 23, 5, 5, 5, 1, 9, 9, 9, 6, 6, 9, 6, 6, 6, 6, 6, 9, 6, 9, 9, 6, 9, 9, 9, 9, 1, 5, 9, 6, 6, 6, 8, 8, 8, 6, 5, 1, 9, 6, 8, 6, 6, 9, 5, 9, 9, 5, 9, 9, 9, 9, 9, 9, 9, 6, 9, 6, 8, 8, 8], "26": [1, 7, 22, 22, 7, 7, 7, 7, 7, 22, 22, 7, 1, 1, 7, 7, 1, 22, 22, 22, 22, 22, 22, 22, 22, 7, 1, 7, 7, 7, 22, 7, 7, 7, 22, 22, 22, 22, 24, 9, 20, 7, 7, 24, 24, 24, 24, 11, 11, 11, 11, 11, 9, 24, 24, 11, 11, 11, 5, 20, 9, 5, 9, 11, 11, 9, 9, 9, 9, 1, 11, 24, 1, 9, 5, 13, 24, 24, 11, 11, 19, 19, 19, 11, 24, 11, 19, 19, 19, 19, 19, 19, 5, 7, 24, 11, 5, 5, 9, 9, 9, 11, 24, 7, 11, 19, 19, 8, 8, 8, 8, 8, 8, 8, 2, 9, 11, 11, 11, 9, 19, 16, 9, 9, 24, 16, 16, 9, 16, 19, 13, 16, 16, 16, 16, 16, 2, 2, 8, 13, 13, 23, 10, 12, 2, 10, 10, 13, 16, 10, 10, 21, 3, 21, 3, 6, 17, 8, 10, 17, 4, 17, 23, 12, 12, 14, 23, 12, 21, 3, 17, 12, 17, 12, 21, 3, 3, 3, 3, 3, 3, 6, 3, 21, 21, 3, 12, 0, 23, 10, 10, 17, 18, 10, 10, 23, 10, 14, 14, 14, 6, 14, 6, 6, 6, 6, 6, 0, 4, 14, 14, 23, 14, 18, 14, 14, 0, 15, 15, 14, 0, 18, 0, 4, 8, 8, 18, 14, 15, 0, 15, 4, 8, 18, 18, 18, 0, 0, 0, 0, 0, 0, 0, 15, 4, 8, 8, 4, 13, 25, 13, 5, 8, 25, 8, 8, 15, 0, 0, 15, 25, 19, 19, 19, 25, 4, 13, 4, 4, 15, 25, 25, 15, 25, 13, 11, 9, 13, 13, 5, 25, 13, 13, 5, 25, 15, 25, 13, 5, 5, 13, 13, 13, 4, 13, 13, 4, 13, 13, 25, 13, 20, 20, 20, 9, 13, 13, 13, 9, 9, 20, 1, 1, 1, 1, 1, 1, 7, 1, 1, 1, 1, 1, 1, 1, 1, 20, 20, 20, 20, 9, 9, 20, 1, 7, 7, 7, 22, 7, 7, 9, 9, 20, 7, 22, 7, 7, 20, 13, 20, 20, 9, 20, 20, 20, 20, 20, 20, 20, 7, 20, 1, 22, 22, 22], "27": [15, 17, 6, 6, 17, 17, 17, 17, 17, 6, 6, 17, 15, 15, 17, 17, 15, 6, 6, 6, 6, 6, 6, 6, 6, 17, 15, 17, 6, 6, 6, 17, 17, 17, 6, 6, 6, 6, 24, 1, 1, 17, 17, 24, 24, 24, 24, 9, 9, 9, 9, 9, 25, 24, 24, 9, 9, 9, 8, 1, 1, 9, 25, 9, 9, 25, 1, 25, 25, 17, 24, 24, 15, 25, 20, 21, 24, 24, 5, 5, 5, 20, 20, 21, 24, 24, 5, 20, 20, 20, 20, 20, 26, 17, 24, 5, 20, 20, 21, 25, 25, 26, 24, 17, 5, 26, 20, 7, 7, 7, 7, 7, 16, 7, 7, 21, 21, 5, 9, 21, 20, 26, 21, 21, 24, 26, 18, 25, 26, 20, 21, 26, 18, 18, 26, 18, 7, 7, 20, 3, 3, 7, 11, 4, 8, 11, 11, 21, 26, 11, 11, 4, 14, 4, 14, 14, 0, 7, 11, 0, 3, 0, 11, 4, 4, 2, 11, 4, 10, 14, 23, 4, 19, 14, 10, 10, 10, 10, 10, 10, 10, 13, 14, 10, 10, 14, 4, 22, 11, 11, 11, 23, 16, 11, 2, 11, 14, 14, 2, 13, 13, 22, 13, 13, 13, 13, 13, 22, 19, 2, 2, 16, 2, 16, 2, 2, 22, 19, 19, 2, 2, 19, 2, 19, 16, 7, 16, 2, 12, 2, 12, 3, 16, 19, 16, 16, 2, 2, 2, 22, 22, 2, 22, 19, 3, 7, 7, 3, 3, 8, 25, 20, 20, 12, 12, 12, 12, 12, 12, 12, 8, 20, 20, 20, 12, 3, 3, 3, 3, 12, 8, 12, 12, 8, 3, 9, 25, 3, 25, 8, 3, 3, 3, 8, 8, 12, 8, 3, 8, 8, 3, 3, 3, 3, 3, 3, 3, 3, 3, 8, 25, 1, 1, 1, 25, 3, 25, 25, 25, 1, 1, 15, 15, 15, 15, 1, 15, 15, 15, 15, 15, 15, 15, 15, 15, 15, 15, 1, 1, 1, 25, 25, 1, 15, 17, 17, 6, 6, 17, 15, 25, 25, 1, 17, 6, 17, 15, 1, 25, 1, 1, 25, 1, 1, 1, 1, 1, 1, 1, 15, 1, 17, 6, 6, 6], "28": [15, 1, 14, 14, 1, 1, 1, 1, 1, 14, 14, 1, 15, 15, 1, 1, 15, 14, 14, 14, 14, 14, 14, 14, 14, 1, 15, 1, 1, 1, 14, 1, 1, 1, 14, 14, 14, 14, 23, 12, 12, 1, 1, 23, 23, 23, 23, 23, 23, 2, 23, 2, 12, 23, 23, 23, 2, 2, 2, 12, 12, 2, 12, 23, 23, 12, 12, 12, 5, 1, 6, 23, 15, 5, 9, 12, 23, 23, 6, 6, 6, 9, 9, 25, 23, 6, 6, 9, 9, 9, 9, 9, 25, 1, 23, 6, 25, 2, 25, 12, 12, 6, 23, 1, 6, 9, 9, 7, 7, 7, 7, 7, 7, 7, 27, 12, 25, 6, 25, 12, 9, 27, 12, 12, 23, 6, 18, 12, 18, 9, 25, 25, 18, 18, 18, 18, 18, 27, 7, 10, 10, 7, 11, 11, 27, 11, 16, 10, 27, 11, 16, 4, 24, 4, 24, 24, 13, 7, 16, 13, 20, 13, 16, 8, 8, 3, 16, 8, 4, 24, 21, 8, 13, 4, 4, 26, 26, 26, 26, 26, 26, 19, 24, 4, 4, 24, 8, 3, 16, 16, 11, 21, 0, 16, 16, 16, 24, 24, 3, 17, 17, 17, 17, 17, 17, 17, 17, 3, 20, 3, 17, 0, 3, 0, 3, 3, 3, 0, 20, 3, 3, 0, 3, 20, 7, 7, 7, 3, 22, 3, 22, 10, 7, 20, 0, 0, 3, 3, 3, 3, 0, 3, 3, 0, 20, 7, 7, 10, 10, 20, 10, 9, 7, 22, 22, 22, 22, 22, 22, 22, 20, 9, 9, 9, 22, 20, 10, 20, 20, 22, 20, 22, 20, 22, 10, 2, 5, 10, 5, 2, 20, 10, 10, 2, 20, 22, 22, 10, 2, 2, 10, 10, 10, 10, 10, 10, 10, 10, 2, 20, 5, 5, 15, 15, 5, 10, 5, 5, 12, 12, 15, 15, 15, 15, 15, 15, 15, 1, 15, 15, 15, 15, 1, 15, 15, 15, 15, 12, 15, 15, 5, 5, 15, 1, 1, 1, 1, 14, 1, 1, 5, 5, 15, 1, 14, 1, 1, 5, 5, 15, 15, 5, 15, 15, 15, 15, 15, 15, 15, 1, 15, 1, 14, 14, 14], "29": [19, 24, 0, 0, 24, 24, 24, 24, 24, 0, 0, 24, 24, 19, 24, 24, 19, 0, 0, 0, 0, 0, 0, 0, 0, 24, 19, 24, 0, 0, 0, 24, 24, 24, 0, 0, 0, 0, 7, 10, 10, 24, 24, 7, 7, 7, 7, 16, 16, 16, 16, 16, 2, 7, 7, 16, 16, 16, 8, 10, 10, 16, 2, 16, 16, 2, 10, 2, 2, 19, 16, 7, 19, 10, 8, 2, 7, 7, 27, 27, 27, 8, 8, 16, 7, 27, 27, 8, 8, 8, 8, 8, 8, 24, 7, 27, 8, 8, 2, 10, 2, 27, 7, 24, 16, 8, 8, 17, 17, 17, 17, 17, 6, 17, 17, 2, 2, 16, 16, 2, 21, 22, 2, 2, 7, 27, 21, 2, 22, 8, 2, 22, 22, 21, 22, 21, 21, 17, 17, 14, 14, 9, 13, 15, 4, 9, 13, 4, 22, 9, 13, 5, 15, 15, 28, 28, 26, 9, 13, 26, 18, 22, 25, 15, 15, 1, 25, 15, 5, 28, 20, 15, 18, 5, 5, 3, 3, 3, 3, 3, 3, 11, 28, 5, 5, 28, 15, 1, 26, 13, 13, 26, 25, 13, 13, 25, 28, 28, 1, 28, 11, 1, 28, 11, 11, 11, 11, 12, 18, 1, 1, 23, 1, 23, 1, 1, 1, 23, 18, 1, 1, 23, 1, 18, 6, 17, 6, 1, 12, 1, 12, 18, 6, 23, 23, 23, 1, 1, 1, 12, 12, 1, 12, 23, 18, 17, 17, 18, 4, 4, 14, 8, 6, 6, 6, 6, 12, 12, 12, 12, 4, 8, 8, 8, 6, 4, 14, 4, 18, 12, 4, 6, 4, 6, 14, 16, 10, 14, 14, 4, 4, 14, 14, 8, 4, 4, 4, 14, 4, 4, 14, 14, 14, 14, 14, 14, 14, 4, 14, 4, 14, 10, 10, 10, 14, 14, 14, 14, 2, 10, 10, 19, 19, 19, 19, 19, 19, 24, 19, 19, 19, 19, 19, 19, 19, 19, 10, 10, 10, 10, 10, 10, 10, 19, 24, 24, 0, 0, 24, 24, 10, 10, 10, 24, 0, 24, 24, 10, 14, 10, 10, 10, 10, 10, 19, 10, 10, 10, 10, 24, 10, 19, 0, 0, 0], "30": [0, 0, 21, 21, 0, 0, 0, 0, 0, 21, 21, 0, 0, 0, 0, 0, 16, 21, 21, 21, 21, 21, 21, 21, 21, 0, 0, 0, 21, 21, 21, 0, 0, 0, 21, 21, 21, 21, 10, 8, 16, 0, 0, 10, 10, 10, 10, 15, 15, 26, 15, 15, 8, 10, 10, 15, 15, 15, 26, 16, 8, 26, 8, 15, 15, 8, 8, 8, 8, 0, 15, 10, 0, 8, 3, 8, 10, 10, 15, 15, 15, 3, 3, 26, 10, 15, 15, 3, 3, 3, 3, 3, 26, 0, 10, 15, 26, 26, 8, 8, 8, 15, 10, 0, 15, 3, 3, 6, 6, 6, 6, 6, 9, 6, 6, 8, 26, 15, 15, 8, 3, 14, 8, 8, 10, 14, 12, 8, 14, 3, 26, 14, 14, 12, 14, 14, 12, 6, 6, 7, 7, 6, 20, 20, 24, 20, 1, 7, 14, 20, 20, 5, 11, 5, 11, 11, 23, 6, 20, 23, 7, 23, 19, 17, 17, 1, 19, 29, 5, 11, 18, 1, 23, 29, 5, 27, 27, 27, 11, 11, 27, 4, 11, 5, 5, 11, 17, 25, 19, 1, 20, 23, 19, 1, 1, 19, 20, 11, 28, 4, 4, 22, 4, 4, 4, 4, 4, 25, 13, 28, 22, 22, 28, 13, 28, 28, 25, 13, 13, 22, 28, 13, 28, 2, 9, 6, 9, 28, 13, 28, 13, 7, 9, 2, 9, 9, 28, 28, 25, 25, 25, 25, 25, 13, 7, 6, 9, 7, 7, 2, 7, 3, 3, 9, 9, 9, 9, 9, 25, 9, 2, 3, 3, 3, 24, 2, 7, 24, 24, 24, 24, 9, 24, 24, 7, 15, 8, 7, 7, 26, 24, 7, 7, 26, 24, 24, 24, 7, 26, 24, 7, 7, 7, 7, 7, 7, 7, 7, 7, 24, 7, 16, 16, 16, 8, 7, 7, 8, 8, 8, 16, 16, 16, 0, 0, 16, 0, 0, 0, 0, 0, 16, 0, 16, 16, 0, 16, 16, 16, 16, 8, 8, 16, 0, 0, 0, 21, 21, 21, 0, 8, 8, 16, 0, 21, 0, 0, 16, 8, 16, 16, 8, 16, 16, 16, 16, 16, 16, 16, 0, 16, 0, 21, 21, 21], "31": [13, 13, 4, 4, 4, 13, 13, 13, 13, 4, 4, 13, 13, 13, 13, 13, 13, 4, 4, 4, 4, 4, 4, 4, 4, 13, 13, 13, 4, 4, 4, 13, 13, 13, 4, 4, 4, 4, 1, 19, 19, 13, 13, 10, 10, 10, 10, 10, 10, 14, 10, 10, 6, 10, 10, 10, 10, 14, 14, 19, 19, 14, 6, 10, 10, 6, 19, 6, 6, 13, 10, 1, 13, 19, 23, 6, 1, 10, 8, 8, 8, 23, 23, 10, 10, 10, 8, 8, 23, 23, 23, 23, 21, 13, 10, 8, 14, 14, 6, 6, 6, 21, 10, 13, 8, 23, 23, 3, 3, 3, 3, 3, 17, 3, 3, 6, 6, 21, 10, 6, 23, 21, 6, 21, 10, 21, 12, 6, 21, 23, 6, 21, 12, 12, 21, 12, 12, 3, 23, 16, 16, 11, 25, 25, 2, 11, 11, 2, 21, 25, 25, 26, 9, 0, 9, 9, 22, 11, 25, 22, 16, 22, 18, 0, 0, 29, 7, 9, 26, 9, 22, 0, 22, 9, 26, 15, 15, 15, 15, 15, 15, 20, 9, 26, 26, 9, 0, 28, 7, 11, 25, 7, 18, 11, 11, 7, 9, 24, 29, 24, 24, 29, 24, 24, 24, 20, 20, 28, 30, 29, 29, 27, 29, 27, 29, 29, 28, 30, 30, 29, 5, 30, 5, 30, 17, 3, 17, 29, 17, 5, 17, 16, 3, 2, 17, 17, 5, 5, 5, 28, 28, 5, 28, 30, 16, 3, 3, 16, 16, 2, 16, 23, 23, 17, 17, 17, 17, 17, 28, 17, 2, 23, 23, 23, 17, 2, 16, 2, 2, 17, 2, 17, 2, 17, 16, 14, 6, 16, 16, 14, 2, 16, 16, 14, 2, 2, 2, 16, 14, 14, 16, 16, 16, 16, 16, 16, 16, 2, 14, 2, 16, 19, 19, 19, 6, 16, 16, 6, 6, 19, 19, 13, 1, 13, 13, 1, 13, 13, 13, 1, 13, 1, 13, 13, 13, 13, 19, 19, 19, 19, 19, 19, 19, 13, 13, 13, 4, 4, 4, 13, 19, 6, 19, 13, 4, 13, 13, 19, 16, 19, 19, 6, 19, 19, 19, 19, 19, 19, 19, 13, 19, 13, 4, 4, 4], "32": [23, 6, 27, 27, 6, 6, 6, 6, 6, 27, 27, 6, 23, 23, 6, 6, 23, 27, 27, 27, 27, 27, 27, 27, 27, 6, 23, 6, 1, 6, 27, 6, 6, 6, 27, 27, 27, 27, 1, 11, 11, 6, 6, 1, 1, 1, 30, 30, 30, 4, 30, 30, 11, 1, 1, 30, 30, 30, 4, 11, 11, 4, 10, 20, 30, 16, 11, 10, 10, 23, 30, 1, 23, 11, 7, 16, 1, 1, 5, 5, 5, 7, 7, 20, 20, 20, 5, 7, 7, 7, 7, 7, 25, 6, 20, 5, 7, 4, 16, 11, 11, 25, 20, 6, 5, 25, 7, 19, 19, 19, 19, 19, 18, 19, 19, 16, 16, 5, 20, 16, 7, 25, 16, 16, 20, 25, 17, 16, 17, 7, 16, 25, 17, 17, 17, 17, 17, 19, 19, 10, 10, 19, 24, 24, 2, 24, 9, 29, 25, 24, 22, 3, 28, 3, 28, 28, 15, 22, 22, 15, 29, 15, 22, 31, 3, 9, 22, 31, 31, 28, 15, 9, 15, 31, 31, 14, 14, 14, 14, 14, 14, 12, 28, 31, 31, 28, 28, 0, 26, 22, 24, 26, 18, 9, 9, 26, 28, 28, 8, 12, 12, 8, 12, 12, 12, 12, 12, 0, 13, 8, 8, 18, 8, 18, 8, 8, 8, 13, 13, 8, 8, 13, 8, 13, 18, 19, 18, 8, 21, 8, 21, 29, 19, 13, 18, 18, 8, 8, 8, 0, 0, 8, 0, 13, 29, 19, 19, 29, 29, 2, 10, 7, 19, 19, 21, 21, 21, 21, 21, 21, 2, 7, 7, 7, 2, 29, 29, 2, 29, 21, 2, 21, 2, 2, 29, 30, 10, 10, 10, 4, 2, 10, 29, 4, 2, 2, 2, 10, 4, 4, 29, 29, 29, 29, 29, 29, 29, 29, 4, 2, 10, 11, 11, 11, 10, 29, 10, 10, 10, 11, 11, 23, 23, 23, 23, 23, 23, 6, 23, 23, 23, 23, 23, 23, 23, 23, 11, 11, 11, 11, 11, 10, 11, 23, 6, 6, 6, 27, 6, 6, 11, 11, 11, 6, 6, 6, 6, 11, 10, 11, 11, 10, 11, 11, 23, 11, 23, 11, 11, 6, 11, 23, 27, 27, 27], "33": [29, 21, 6, 6, 21, 21, 21, 21, 21, 6, 6, 21, 21, 29, 21, 21, 29, 6, 6, 6, 6, 6, 6, 6, 6, 21, 29, 21, 6, 6, 6, 21, 21, 21, 6, 6, 6, 6, 17, 1, 1, 29, 29, 17, 17, 17, 3, 3, 3, 3, 3, 3, 7, 17, 17, 3, 3, 3, 19, 1, 1, 19, 7, 3, 3, 7, 1, 7, 7, 29, 18, 17, 29, 1, 5, 7, 17, 17, 18, 18, 18, 5, 5, 17, 17, 18, 18, 5, 5, 5, 5, 5, 5, 29, 17, 18, 5, 19, 20, 7, 7, 18, 17, 21, 18, 5, 5, 14, 14, 14, 14, 14, 14, 14, 14, 1, 20, 18, 3, 20, 5, 10, 20, 20, 17, 18, 10, 7, 10, 5, 20, 5, 10, 10, 10, 10, 10, 14, 14, 7, 7, 28, 11, 11, 14, 11, 23, 20, 20, 11, 11, 8, 32, 8, 16, 16, 9, 28, 11, 31, 13, 31, 28, 11, 8, 23, 28, 32, 32, 32, 15, 23, 25, 32, 12, 12, 12, 12, 12, 12, 12, 16, 32, 32, 32, 32, 2, 22, 23, 23, 11, 15, 28, 23, 24, 28, 11, 4, 4, 4, 4, 22, 4, 4, 27, 27, 27, 30, 25, 24, 4, 22, 24, 26, 24, 24, 30, 25, 25, 22, 30, 25, 30, 25, 14, 24, 26, 24, 26, 30, 26, 13, 14, 25, 26, 26, 30, 30, 30, 30, 26, 30, 30, 25, 13, 14, 14, 13, 13, 0, 7, 5, 14, 14, 26, 26, 26, 26, 26, 26, 0, 5, 5, 5, 0, 13, 13, 0, 13, 0, 0, 0, 0, 0, 13, 3, 7, 13, 7, 19, 13, 7, 13, 19, 0, 0, 0, 13, 19, 19, 13, 13, 13, 13, 13, 13, 13, 13, 19, 13, 7, 1, 1, 1, 7, 13, 7, 7, 7, 1, 1, 29, 29, 29, 29, 1, 29, 21, 29, 29, 29, 29, 29, 29, 29, 29, 1, 1, 1, 1, 1, 7, 1, 29, 21, 29, 6, 6, 21, 21, 7, 7, 1, 29, 21, 29, 21, 1, 7, 1, 1, 7, 1, 1, 1, 1, 1, 1, 1, 21, 1, 29, 6, 6, 6], "34": [13, 25, 27, 27, 25, 25, 25, 25, 25, 27, 27, 25, 13, 13, 2, 2, 13, 27, 27, 27, 27, 27, 27, 27, 27, 25, 13, 2, 2, 2, 27, 25, 25, 25, 27, 27, 27, 2, 8, 4, 4, 2, 2, 2, 8, 8, 8, 32, 32, 32, 32, 32, 4, 8, 8, 32, 32, 32, 24, 4, 4, 32, 4, 32, 32, 23, 4, 4, 0, 13, 21, 8, 13, 4, 24, 23, 8, 8, 21, 21, 21, 24, 24, 23, 8, 21, 21, 24, 24, 24, 24, 24, 24, 13, 8, 21, 24, 24, 23, 4, 23, 21, 8, 25, 32, 5, 24, 7, 7, 7, 7, 7, 7, 7, 5, 23, 23, 21, 32, 23, 24, 5, 23, 23, 8, 21, 5, 23, 5, 24, 23, 5, 17, 17, 5, 17, 5, 12, 7, 0, 0, 7, 10, 9, 12, 9, 9, 18, 12, 29, 29, 19, 15, 31, 15, 15, 16, 29, 29, 16, 18, 12, 20, 31, 31, 9, 20, 1, 19, 15, 30, 31, 26, 1, 19, 14, 14, 14, 14, 14, 14, 6, 33, 19, 19, 15, 31, 22, 20, 29, 10, 28, 20, 9, 9, 20, 10, 10, 3, 33, 6, 33, 33, 6, 6, 6, 6, 22, 26, 3, 33, 20, 3, 26, 3, 3, 22, 26, 26, 3, 3, 26, 3, 26, 7, 7, 11, 3, 11, 3, 11, 0, 7, 26, 11, 11, 3, 3, 22, 22, 22, 22, 22, 26, 0, 7, 7, 0, 18, 18, 0, 24, 7, 7, 11, 11, 11, 11, 22, 11, 18, 24, 24, 24, 11, 18, 0, 18, 18, 11, 18, 11, 18, 11, 0, 32, 4, 0, 0, 18, 18, 0, 0, 24, 18, 11, 18, 0, 18, 18, 0, 0, 0, 0, 0, 0, 0, 18, 0, 18, 0, 4, 4, 4, 0, 0, 0, 0, 4, 4, 4, 13, 13, 13, 13, 13, 13, 2, 13, 13, 13, 13, 13, 13, 13, 13, 4, 4, 4, 4, 4, 4, 4, 13, 25, 25, 2, 25, 25, 2, 4, 4, 4, 13, 25, 25, 25, 4, 0, 4, 4, 4, 4, 4, 13, 4, 13, 4, 4, 25, 4, 13, 25, 27, 25], "35": [27, 2, 26, 26, 26, 2, 2, 2, 26, 26, 26, 2, 27, 27, 2, 2, 27, 26, 10, 10, 26, 26, 10, 10, 10, 2, 27, 2, 26, 26, 26, 2, 2, 26, 10, 10, 10, 26, 33, 19, 19, 2, 2, 33, 33, 33, 16, 16, 16, 16, 16, 16, 12, 33, 9, 16, 16, 16, 0, 19, 19, 0, 12, 16, 16, 12, 12, 12, 12, 27, 9, 33, 27, 19, 18, 12, 33, 9, 9, 9, 18, 18, 18, 33, 33, 33, 18, 18, 18, 18, 18, 18, 6, 2, 33, 6, 18, 0, 20, 12, 12, 6, 33, 2, 16, 6, 18, 3, 3, 3, 3, 21, 17, 3, 3, 20, 20, 9, 16, 20, 18, 6, 20, 12, 33, 6, 14, 12, 14, 18, 20, 6, 14, 14, 14, 14, 3, 3, 3, 28, 28, 3, 13, 29, 11, 13, 29, 4, 14, 13, 13, 5, 8, 5, 8, 8, 15, 3, 13, 25, 4, 25, 31, 8, 8, 24, 31, 8, 5, 23, 15, 29, 15, 8, 5, 23, 23, 23, 23, 23, 23, 32, 1, 5, 5, 23, 8, 22, 29, 13, 13, 15, 31, 29, 24, 31, 8, 1, 1, 1, 1, 1, 1, 32, 32, 32, 32, 22, 30, 24, 1, 17, 24, 17, 24, 24, 22, 30, 30, 24, 22, 17, 24, 30, 17, 3, 17, 24, 7, 22, 7, 30, 21, 17, 17, 17, 24, 22, 22, 22, 22, 22, 22, 30, 30, 21, 21, 4, 4, 34, 28, 18, 21, 21, 21, 21, 7, 7, 22, 7, 34, 18, 18, 18, 7, 4, 4, 34, 34, 7, 34, 21, 34, 21, 4, 16, 28, 4, 28, 0, 34, 28, 4, 0, 34, 7, 34, 4, 0, 0, 4, 4, 4, 4, 4, 4, 4, 4, 0, 34, 28, 19, 19, 19, 28, 4, 28, 28, 12, 19, 19, 27, 27, 27, 27, 27, 27, 2, 27, 27, 27, 27, 2, 27, 27, 27, 19, 19, 19, 19, 19, 28, 19, 27, 2, 2, 26, 26, 26, 2, 19, 12, 19, 2, 26, 2, 2, 19, 28, 19, 19, 28, 19, 19, 27, 19, 19, 19, 19, 2, 19, 27, 26, 26, 26], "36": [3, 3, 32, 32, 10, 3, 3, 3, 10, 10, 32, 10, 3, 3, 3, 3, 23, 32, 32, 32, 32, 10, 32, 32, 32, 3, 3, 10, 32, 10, 32, 3, 3, 10, 32, 32, 32, 32, 11, 8, 23, 3, 3, 11, 11, 11, 11, 20, 20, 20, 20, 20, 8, 11, 11, 20, 20, 20, 28, 23, 8, 20, 18, 20, 20, 8, 8, 8, 18, 3, 11, 11, 3, 8, 28, 18, 11, 11, 11, 16, 16, 16, 28, 1, 11, 1, 16, 16, 16, 28, 28, 28, 28, 3, 11, 16, 28, 28, 33, 8, 8, 1, 1, 3, 16, 28, 9, 19, 19, 19, 19, 19, 14, 19, 4, 33, 1, 1, 1, 33, 16, 4, 33, 1, 11, 1, 24, 8, 4, 9, 33, 1, 24, 24, 24, 24, 4, 4, 9, 18, 18, 19, 13, 13, 4, 13, 13, 7, 4, 13, 13, 2, 22, 2, 22, 22, 21, 19, 13, 21, 7, 21, 26, 13, 2, 5, 26, 6, 25, 22, 34, 34, 31, 6, 25, 35, 35, 35, 35, 35, 35, 27, 6, 25, 25, 22, 30, 17, 30, 13, 13, 30, 15, 13, 29, 26, 13, 12, 12, 12, 12, 12, 12, 12, 27, 27, 27, 17, 31, 29, 12, 15, 29, 15, 29, 29, 17, 0, 31, 29, 17, 0, 5, 31, 14, 19, 14, 29, 14, 17, 14, 7, 14, 31, 14, 15, 29, 17, 17, 17, 17, 17, 17, 0, 7, 19, 19, 7, 7, 7, 18, 9, 9, 14, 14, 14, 14, 14, 17, 14, 9, 28, 28, 28, 14, 7, 7, 7, 7, 14, 14, 14, 14, 14, 18, 20, 8, 18, 18, 28, 7, 18, 18, 28, 14, 14, 14, 18, 28, 28, 7, 7, 7, 7, 7, 7, 7, 7, 18, 7, 18, 23, 23, 23, 8, 7, 18, 18, 8, 8, 23, 23, 23, 3, 3, 23, 3, 3, 3, 3, 3, 3, 3, 23, 3, 3, 23, 23, 23, 23, 8, 18, 23, 3, 3, 3, 10, 10, 10, 3, 8, 8, 23, 3, 10, 3, 3, 8, 18, 23, 23, 8, 23, 23, 23, 23, 23, 23, 23, 3, 23, 3, 10, 10, 10], "37": [21, 3, 22, 22, 3, 3, 3, 3, 3, 22, 22, 3, 21, 21, 3, 3, 21, 22, 22, 22, 22, 22, 22, 22, 22, 3, 21, 3, 3, 3, 22, 3, 3, 3, 22, 22, 22, 22, 33, 24, 1, 3, 3, 33, 33, 33, 9, 9, 9, 9, 9, 9, 24, 33, 33, 9, 9, 9, 35, 1, 24, 35, 1, 9, 9, 24, 24, 24, 27, 21, 9, 33, 21, 24, 6, 27, 33, 33, 4, 4, 4, 32, 32, 26, 33, 26, 4, 32, 32, 32, 32, 6, 6, 21, 33, 4, 6, 6, 27, 24, 24, 26, 26, 3, 4, 6, 32, 20, 20, 20, 20, 20, 5, 20, 20, 24, 26, 4, 26, 24, 32, 6, 24, 26, 33, 26, 0, 24, 18, 6, 27, 26, 18, 0, 18, 18, 0, 20, 20, 8, 27, 20, 31, 31, 16, 31, 31, 27, 18, 31, 30, 10, 2, 36, 2, 2, 34, 20, 30, 13, 8, 13, 17, 31, 36, 25, 17, 10, 10, 2, 12, 36, 19, 10, 10, 23, 23, 23, 23, 23, 23, 15, 2, 10, 10, 2, 29, 28, 17, 30, 31, 34, 5, 30, 25, 17, 2, 2, 25, 15, 15, 7, 15, 15, 15, 15, 15, 7, 19, 25, 25, 17, 25, 5, 25, 25, 7, 19, 19, 25, 7, 19, 25, 19, 5, 20, 5, 25, 19, 7, 16, 8, 20, 19, 5, 5, 25, 7, 7, 7, 7, 7, 7, 19, 8, 20, 14, 8, 8, 16, 27, 6, 6, 14, 14, 14, 14, 14, 14, 14, 16, 6, 6, 6, 16, 8, 8, 16, 8, 16, 16, 14, 16, 35, 27, 9, 24, 27, 27, 35, 8, 8, 27, 35, 35, 16, 16, 27, 35, 35, 8, 8, 8, 8, 8, 8, 8, 8, 27, 35, 1, 1, 11, 11, 24, 8, 1, 27, 24, 24, 11, 21, 21, 21, 21, 11, 21, 3, 21, 21, 21, 21, 21, 21, 21, 21, 11, 11, 11, 11, 24, 1, 1, 21, 3, 3, 3, 22, 3, 3, 1, 24, 11, 21, 3, 3, 3, 11, 1, 11, 11, 1, 11, 11, 11, 11, 11, 11, 11, 3, 11, 21, 22, 22, 22], "38": [36, 4, 13, 13, 4, 4, 4, 4, 4, 13, 13, 4, 36, 36, 10, 10, 36, 13, 13, 13, 13, 13, 13, 13, 13, 4, 10, 4, 13, 13, 13, 4, 4, 4, 13, 13, 13, 13, 10, 0, 0, 10, 10, 6, 6, 6, 14, 14, 14, 14, 14, 14, 0, 6, 6, 14, 14, 14, 12, 0, 0, 12, 0, 14, 14, 22, 0, 0, 15, 10, 14, 6, 36, 0, 2, 15, 6, 6, 31, 31, 31, 18, 18, 22, 6, 6, 31, 18, 18, 18, 18, 18, 2, 4, 6, 31, 2, 2, 22, 0, 0, 31, 6, 4, 31, 18, 2, 20, 20, 20, 20, 20, 24, 20, 7, 22, 22, 37, 22, 22, 18, 17, 22, 22, 6, 17, 17, 0, 17, 2, 22, 17, 17, 17, 17, 17, 7, 7, 24, 15, 15, 20, 30, 30, 7, 30, 27, 15, 17, 30, 28, 26, 34, 34, 34, 34, 21, 20, 28, 21, 35, 21, 9, 3, 34, 27, 9, 34, 26, 34, 29, 29, 16, 34, 26, 5, 5, 5, 5, 5, 5, 25, 11, 26, 26, 5, 3, 1, 9, 28, 30, 23, 9, 27, 27, 9, 34, 11, 1, 11, 25, 11, 11, 25, 25, 25, 25, 1, 35, 19, 11, 19, 19, 16, 19, 19, 1, 16, 16, 19, 1, 16, 1, 16, 24, 20, 33, 19, 8, 1, 8, 35, 24, 16, 33, 33, 1, 1, 1, 1, 33, 1, 1, 16, 35, 24, 20, 35, 32, 8, 15, 2, 24, 24, 33, 33, 33, 33, 33, 8, 2, 2, 18, 18, 8, 32, 32, 8, 35, 8, 8, 24, 8, 24, 15, 14, 0, 15, 15, 12, 32, 15, 32, 12, 12, 8, 8, 32, 12, 12, 32, 32, 32, 35, 32, 32, 35, 32, 32, 12, 15, 0, 36, 0, 0, 32, 15, 15, 0, 0, 36, 36, 36, 10, 10, 36, 10, 10, 10, 10, 36, 36, 10, 36, 36, 36, 36, 0, 36, 0, 0, 0, 0, 10, 4, 4, 13, 13, 4, 10, 0, 0, 0, 4, 13, 4, 4, 0, 15, 36, 0, 0, 36, 36, 36, 36, 36, 36, 36, 4, 36, 4, 13, 13, 13], "39": [7, 0, 16, 16, 0, 0, 0, 0, 0, 16, 16, 0, 27, 7, 27, 27, 7, 16, 16, 16, 16, 16, 16, 16, 16, 27, 27, 0, 16, 16, 16, 0, 0, 0, 16, 16, 16, 16, 25, 24, 24, 27, 27, 25, 25, 25, 25, 5, 5, 37, 37, 5, 24, 25, 25, 5, 5, 5, 9, 24, 24, 9, 2, 37, 37, 24, 24, 24, 2, 0, 5, 25, 7, 24, 14, 2, 25, 25, 5, 5, 5, 14, 14, 37, 25, 5, 5, 14, 14, 14, 14, 14, 33, 0, 25, 5, 14, 9, 10, 24, 24, 33, 25, 27, 5, 33, 14, 36, 36, 36, 1, 1, 1, 36, 36, 10, 37, 5, 37, 10, 14, 33, 10, 10, 25, 13, 13, 24, 13, 14, 10, 33, 13, 13, 13, 13, 36, 36, 36, 2, 2, 36, 26, 26, 35, 26, 3, 29, 33, 26, 32, 18, 18, 18, 18, 18, 30, 36, 32, 30, 8, 30, 15, 21, 18, 3, 15, 21, 34, 4, 20, 3, 30, 21, 18, 19, 19, 19, 19, 19, 19, 38, 4, 17, 18, 4, 21, 6, 3, 32, 32, 20, 15, 3, 3, 15, 32, 23, 12, 23, 31, 23, 23, 31, 31, 31, 31, 6, 8, 12, 23, 15, 12, 15, 12, 12, 6, 11, 11, 12, 12, 11, 6, 11, 1, 36, 28, 12, 28, 12, 28, 8, 1, 11, 28, 28, 12, 12, 6, 6, 6, 6, 6, 11, 8, 1, 1, 8, 29, 22, 2, 14, 1, 1, 1, 1, 28, 28, 6, 28, 22, 14, 14, 14, 28, 29, 29, 22, 22, 28, 22, 1, 22, 22, 29, 37, 24, 2, 2, 9, 22, 2, 29, 9, 22, 22, 22, 29, 9, 9, 29, 29, 29, 29, 29, 29, 29, 29, 9, 22, 2, 24, 7, 7, 24, 29, 2, 2, 24, 24, 7, 7, 7, 27, 27, 7, 27, 27, 27, 27, 7, 7, 27, 7, 7, 7, 7, 24, 7, 24, 24, 2, 7, 27, 0, 0, 16, 16, 0, 27, 24, 24, 7, 0, 16, 0, 27, 24, 2, 7, 7, 24, 7, 7, 7, 7, 7, 7, 7, 27, 7, 0, 16, 16, 16], "40": [2, 39, 8, 8, 39, 39, 39, 39, 39, 8, 8, 39, 2, 2, 39, 17, 2, 8, 8, 8, 8, 8, 8, 8, 8, 39, 2, 39, 17, 8, 8, 39, 39, 39, 8, 8, 8, 8, 17, 12, 12, 39, 17, 17, 17, 17, 0, 0, 0, 0, 0, 0, 12, 17, 22, 0, 0, 0, 30, 12, 12, 0, 12, 0, 0, 12, 12, 12, 29, 39, 22, 17, 2, 12, 30, 24, 17, 22, 22, 19, 19, 19, 30, 22, 22, 22, 19, 19, 19, 30, 30, 5, 30, 39, 22, 19, 30, 30, 24, 12, 12, 22, 22, 39, 19, 30, 30, 36, 36, 36, 21, 21, 21, 21, 36, 24, 24, 22, 0, 24, 36, 9, 24, 24, 22, 9, 9, 24, 9, 30, 24, 9, 9, 9, 9, 9, 36, 27, 31, 29, 29, 36, 14, 14, 27, 34, 1, 3, 9, 34, 11, 4, 26, 4, 26, 26, 10, 36, 11, 38, 15, 38, 35, 18, 18, 1, 35, 18, 4, 26, 20, 18, 15, 18, 4, 23, 23, 23, 23, 23, 23, 13, 26, 4, 4, 26, 32, 6, 33, 11, 14, 33, 37, 11, 1, 35, 14, 11, 25, 16, 16, 6, 16, 16, 16, 16, 16, 6, 15, 25, 25, 37, 25, 28, 25, 25, 6, 28, 15, 25, 25, 28, 25, 15, 21, 36, 7, 25, 7, 25, 7, 15, 21, 15, 37, 37, 25, 25, 25, 6, 6, 25, 6, 28, 15, 21, 21, 15, 3, 31, 29, 30, 5, 5, 21, 21, 7, 7, 6, 7, 31, 30, 30, 5, 7, 3, 3, 3, 3, 7, 31, 5, 31, 5, 3, 0, 29, 29, 29, 3, 3, 29, 3, 30, 5, 7, 5, 29, 30, 3, 3, 3, 3, 3, 29, 3, 3, 3, 3, 3, 29, 12, 12, 12, 29, 3, 29, 29, 12, 12, 2, 2, 2, 2, 2, 2, 2, 17, 2, 17, 2, 2, 2, 2, 2, 2, 2, 12, 2, 12, 12, 12, 12, 17, 39, 39, 8, 8, 39, 17, 12, 12, 12, 39, 8, 39, 39, 12, 29, 2, 12, 12, 2, 2, 2, 2, 2, 2, 12, 39, 2, 39, 8, 8, 8], "41": [1, 10, 38, 38, 10, 10, 10, 10, 10, 38, 38, 10, 1, 1, 10, 10, 1, 38, 7, 7, 38, 38, 7, 7, 7, 10, 1, 10, 38, 38, 7, 10, 10, 10, 7, 7, 7, 38, 18, 11, 11, 10, 10, 18, 18, 18, 18, 4, 4, 4, 4, 4, 34, 18, 18, 4, 4, 4, 23, 11, 11, 23, 33, 4, 4, 34, 11, 34, 33, 1, 4, 18, 1, 11, 13, 34, 18, 18, 37, 37, 37, 13, 13, 12, 18, 18, 37, 13, 13, 13, 13, 13, 12, 10, 18, 37, 13, 23, 34, 11, 34, 12, 12, 10, 37, 13, 13, 8, 8, 8, 8, 8, 35, 8, 8, 34, 34, 12, 34, 34, 13, 21, 34, 34, 18, 21, 21, 34, 21, 13, 34, 21, 21, 21, 21, 17, 8, 8, 13, 33, 33, 20, 31, 31, 2, 19, 19, 28, 21, 19, 32, 3, 9, 3, 9, 9, 14, 20, 32, 14, 22, 14, 36, 3, 3, 30, 36, 3, 40, 9, 29, 29, 22, 3, 24, 24, 24, 24, 24, 24, 24, 27, 9, 39, 24, 9, 3, 0, 15, 32, 31, 15, 36, 32, 30, 36, 9, 6, 6, 6, 27, 6, 6, 27, 27, 27, 27, 0, 22, 30, 6, 30, 6, 30, 30, 6, 25, 16, 22, 6, 25, 16, 25, 22, 35, 8, 35, 30, 16, 25, 16, 22, 26, 22, 35, 35, 25, 25, 25, 0, 0, 25, 0, 16, 22, 8, 26, 22, 28, 2, 33, 13, 13, 26, 26, 26, 26, 26, 0, 26, 2, 13, 13, 13, 26, 28, 5, 2, 28, 16, 2, 26, 2, 26, 28, 12, 33, 28, 33, 23, 5, 33, 28, 23, 5, 2, 2, 28, 23, 23, 28, 28, 5, 28, 28, 28, 28, 28, 5, 5, 33, 11, 11, 11, 33, 28, 33, 33, 34, 11, 11, 1, 1, 1, 1, 1, 1, 10, 1, 1, 1, 1, 1, 1, 1, 1, 11, 11, 11, 11, 11, 33, 11, 1, 10, 10, 38, 38, 38, 10, 11, 11, 11, 10, 38, 10, 10, 11, 33, 11, 11, 33, 11, 11, 1, 11, 11, 11, 11, 10, 11, 1, 38, 38, 38], "42": [34, 14, 2, 2, 14, 14, 14, 14, 14, 2, 2, 14, 34, 34, 14, 14, 34, 2, 2, 2, 2, 2, 2, 2, 2, 14, 34, 14, 14, 14, 2, 14, 14, 14, 2, 2, 2, 2, 16, 5, 32, 14, 14, 16, 16, 16, 17, 17, 17, 17, 17, 17, 5, 16, 16, 17, 17, 17, 21, 32, 5, 21, 9, 17, 17, 5, 5, 5, 9, 34, 16, 16, 34, 5, 21, 9, 16, 16, 16, 30, 30, 30, 30, 1, 16, 16, 30, 30, 30, 30, 30, 21, 21, 14, 16, 12, 21, 21, 38, 5, 5, 12, 16, 14, 30, 12, 21, 8, 8, 8, 8, 8, 27, 8, 8, 38, 1, 16, 1, 38, 30, 12, 38, 1, 16, 12, 26, 5, 11, 21, 38, 12, 26, 26, 12, 11, 11, 8, 8, 9, 9, 8, 25, 25, 27, 35, 35, 29, 11, 25, 20, 6, 24, 28, 24, 22, 19, 8, 20, 19, 10, 19, 0, 25, 28, 35, 0, 6, 6, 7, 40, 23, 15, 6, 6, 36, 36, 36, 24, 24, 36, 22, 7, 6, 6, 24, 39, 4, 35, 20, 25, 18, 0, 35, 13, 0, 7, 7, 13, 7, 31, 13, 7, 7, 31, 31, 31, 4, 15, 13, 13, 27, 13, 33, 13, 13, 41, 33, 15, 13, 41, 33, 41, 15, 27, 8, 27, 13, 37, 41, 37, 10, 27, 29, 27, 3, 41, 41, 41, 4, 4, 41, 41, 37, 10, 8, 3, 10, 10, 29, 9, 21, 21, 3, 3, 3, 3, 3, 3, 37, 29, 21, 21, 21, 3, 29, 10, 29, 10, 37, 29, 3, 29, 3, 9, 17, 5, 9, 9, 21, 10, 9, 9, 21, 29, 37, 29, 9, 21, 21, 10, 10, 10, 10, 10, 10, 10, 10, 9, 10, 9, 32, 32, 32, 5, 10, 9, 9, 5, 5, 32, 34, 34, 34, 34, 34, 34, 14, 34, 34, 34, 34, 34, 34, 34, 34, 32, 32, 32, 32, 5, 9, 32, 34, 14, 14, 14, 2, 14, 34, 5, 5, 32, 14, 2, 14, 14, 32, 9, 32, 32, 5, 32, 32, 32, 32, 32, 32, 32, 14, 32, 34, 2, 2, 2], "43": [12, 20, 0, 0, 20, 20, 20, 20, 20, 0, 0, 20, 12, 12, 20, 20, 12, 0, 28, 28, 0, 0, 28, 0, 28, 20, 16, 20, 0, 0, 0, 20, 20, 20, 28, 28, 28, 0, 16, 4, 36, 20, 16, 11, 11, 11, 11, 21, 21, 21, 21, 21, 4, 11, 11, 21, 21, 21, 32, 36, 4, 32, 31, 21, 21, 4, 4, 4, 31, 12, 11, 16, 12, 4, 33, 31, 16, 11, 5, 5, 5, 33, 33, 38, 11, 38, 5, 33, 33, 33, 33, 33, 32, 12, 16, 5, 33, 32, 41, 4, 4, 38, 38, 20, 5, 26, 33, 23, 23, 23, 23, 23, 7, 23, 23, 41, 41, 5, 38, 41, 8, 26, 41, 41, 38, 38, 8, 4, 26, 33, 41, 26, 8, 8, 8, 8, 8, 23, 10, 31, 2, 23, 22, 14, 10, 22, 30, 2, 26, 22, 22, 18, 19, 18, 19, 19, 42, 23, 22, 37, 17, 25, 9, 14, 14, 30, 9, 18, 39, 3, 13, 13, 25, 18, 18, 3, 3, 3, 3, 3, 3, 35, 27, 18, 18, 3, 14, 40, 9, 22, 22, 24, 7, 30, 30, 9, 19, 27, 1, 27, 27, 9, 27, 27, 35, 35, 35, 40, 17, 1, 1, 9, 1, 7, 1, 1, 15, 29, 29, 1, 15, 29, 15, 29, 10, 23, 7, 1, 34, 15, 34, 17, 10, 7, 7, 7, 15, 15, 15, 15, 40, 15, 15, 29, 17, 23, 23, 17, 2, 34, 31, 33, 10, 6, 40, 40, 40, 40, 40, 40, 10, 33, 33, 33, 6, 2, 2, 34, 17, 34, 34, 6, 34, 6, 2, 21, 4, 2, 31, 32, 2, 31, 2, 32, 6, 34, 6, 2, 32, 32, 2, 2, 2, 17, 17, 2, 17, 2, 2, 2, 31, 36, 36, 36, 4, 2, 31, 31, 4, 4, 36, 12, 16, 16, 16, 16, 16, 16, 12, 16, 12, 16, 16, 12, 12, 12, 36, 36, 36, 36, 4, 31, 36, 16, 20, 12, 0, 0, 0, 20, 4, 4, 36, 12, 0, 12, 20, 36, 31, 36, 36, 31, 36, 36, 36, 36, 36, 36, 36, 20, 36, 12, 0, 0, 0], "44": [14, 28, 12, 12, 28, 28, 28, 28, 28, 12, 12, 28, 14, 14, 1, 1, 14, 12, 12, 12, 12, 12, 12, 12, 12, 1, 14, 28, 28, 28, 12, 28, 28, 28, 12, 12, 12, 12, 1, 4, 24, 1, 1, 1, 21, 21, 21, 21, 21, 9, 21, 21, 4, 15, 21, 21, 21, 9, 9, 24, 4, 9, 42, 21, 21, 4, 4, 4, 42, 14, 21, 15, 14, 4, 6, 20, 15, 21, 41, 41, 41, 6, 6, 15, 15, 15, 41, 6, 6, 6, 6, 6, 9, 14, 15, 38, 6, 9, 20, 4, 4, 38, 15, 1, 41, 6, 6, 16, 16, 16, 16, 16, 36, 16, 0, 20, 20, 41, 15, 20, 10, 0, 20, 20, 15, 38, 10, 4, 26, 6, 20, 38, 26, 26, 26, 26, 10, 0, 16, 42, 42, 16, 22, 22, 37, 18, 18, 23, 0, 22, 22, 43, 3, 17, 3, 3, 11, 16, 22, 40, 8, 40, 2, 22, 17, 34, 33, 3, 43, 31, 29, 17, 35, 3, 43, 19, 19, 19, 19, 19, 19, 13, 31, 30, 43, 3, 17, 25, 33, 18, 22, 33, 2, 18, 18, 33, 31, 31, 7, 39, 39, 39, 39, 39, 13, 13, 13, 5, 8, 7, 39, 36, 7, 36, 7, 7, 25, 27, 27, 7, 25, 27, 7, 8, 36, 16, 36, 7, 27, 25, 27, 8, 36, 8, 36, 5, 7, 7, 25, 25, 5, 25, 25, 27, 8, 16, 16, 8, 23, 8, 42, 6, 6, 32, 5, 5, 5, 5, 5, 5, 32, 6, 6, 6, 32, 8, 23, 8, 8, 27, 32, 32, 8, 32, 23, 9, 4, 23, 42, 9, 23, 42, 23, 9, 32, 32, 32, 23, 9, 32, 23, 23, 23, 23, 23, 23, 23, 23, 23, 32, 42, 24, 24, 24, 4, 23, 42, 42, 4, 4, 24, 14, 14, 14, 1, 14, 1, 1, 1, 1, 14, 14, 1, 14, 14, 14, 24, 24, 24, 24, 4, 42, 24, 1, 28, 28, 28, 28, 28, 1, 4, 4, 24, 14, 28, 28, 1, 24, 42, 24, 24, 42, 24, 24, 24, 24, 24, 24, 24, 1, 24, 14, 28, 28, 28], "45": [1, 24, 6, 31, 35, 24, 24, 35, 24, 31, 6, 35, 35, 1, 24, 35, 1, 31, 6, 6, 31, 6, 6, 6, 6, 35, 1, 31, 31, 31, 6, 35, 35, 24, 6, 6, 6, 35, 18, 39, 20, 24, 24, 18, 18, 18, 18, 37, 37, 37, 37, 37, 39, 18, 18, 37, 37, 37, 34, 20, 44, 34, 39, 5, 37, 44, 44, 39, 33, 24, 18, 18, 1, 39, 2, 7, 18, 18, 21, 21, 21, 2, 2, 5, 18, 5, 21, 2, 2, 2, 2, 2, 34, 24, 18, 21, 34, 34, 44, 39, 39, 21, 5, 35, 21, 2, 2, 13, 13, 13, 13, 13, 16, 13, 13, 44, 7, 21, 5, 44, 2, 27, 44, 7, 18, 27, 27, 39, 9, 2, 7, 27, 27, 27, 27, 9, 9, 9, 2, 33, 33, 13, 12, 30, 22, 36, 36, 33, 9, 41, 12, 19, 42, 26, 42, 42, 14, 13, 12, 28, 3, 28, 43, 30, 26, 36, 11, 19, 19, 42, 14, 40, 14, 19, 19, 4, 4, 4, 42, 42, 4, 15, 42, 19, 19, 42, 17, 38, 11, 36, 12, 29, 43, 36, 36, 11, 12, 32, 0, 32, 0, 32, 32, 15, 15, 15, 15, 10, 3, 8, 32, 8, 8, 23, 8, 8, 10, 23, 3, 8, 0, 23, 10, 3, 16, 13, 16, 8, 22, 10, 22, 3, 16, 3, 16, 16, 8, 8, 10, 10, 10, 10, 10, 23, 3, 13, 16, 3, 25, 22, 33, 2, 2, 16, 16, 16, 16, 16, 10, 16, 22, 2, 2, 2, 22, 25, 25, 22, 3, 22, 22, 16, 22, 22, 33, 37, 39, 33, 33, 34, 25, 33, 25, 34, 22, 22, 22, 25, 34, 34, 25, 25, 25, 25, 33, 25, 25, 25, 25, 25, 33, 20, 20, 20, 39, 25, 33, 33, 39, 39, 20, 1, 1, 1, 1, 1, 1, 35, 1, 1, 1, 1, 1, 1, 1, 1, 20, 20, 20, 20, 39, 39, 20, 1, 35, 24, 31, 31, 31, 35, 39, 39, 20, 24, 35, 24, 35, 20, 33, 20, 20, 39, 20, 20, 20, 20, 20, 20, 20, 35, 20, 24, 31, 31, 31], "46": [18, 3, 0, 0, 32, 32, 32, 32, 32, 0, 0, 32, 18, 3, 32, 32, 18, 0, 0, 0, 0, 0, 0, 0, 0, 32, 20, 32, 32, 32, 0, 32, 32, 3, 0, 0, 0, 32, 20, 5, 5, 20, 20, 44, 44, 44, 44, 28, 28, 28, 28, 28, 5, 44, 44, 28, 28, 28, 15, 5, 5, 15, 5, 28, 28, 25, 5, 5, 9, 3, 28, 20, 20, 5, 36, 9, 20, 44, 6, 8, 8, 8, 36, 6, 6, 6, 8, 8, 8, 36, 36, 36, 38, 3, 6, 8, 36, 15, 25, 5, 5, 38, 6, 32, 8, 27, 36, 2, 2, 2, 2, 12, 24, 2, 27, 25, 43, 38, 28, 25, 8, 27, 25, 38, 6, 38, 10, 5, 34, 34, 43, 38, 10, 10, 38, 10, 10, 22, 34, 9, 9, 2, 40, 40, 22, 14, 40, 43, 43, 14, 14, 33, 31, 21, 31, 31, 11, 2, 14, 11, 37, 22, 23, 40, 21, 26, 39, 7, 33, 31, 41, 21, 37, 7, 33, 13, 13, 13, 13, 13, 13, 4, 7, 33, 33, 31, 21, 35, 39, 14, 14, 29, 23, 14, 2, 39, 31, 31, 35, 4, 4, 17, 4, 4, 4, 4, 4, 42, 37, 17, 17, 17, 17, 16, 17, 17, 35, 16, 37, 17, 35, 16, 42, 37, 24, 2, 24, 17, 30, 42, 30, 37, 24, 37, 24, 24, 42, 42, 42, 42, 42, 42, 42, 16, 37, 24, 12, 37, 19, 1, 9, 36, 36, 12, 12, 12, 30, 12, 42, 30, 1, 36, 36, 36, 1, 45, 45, 1, 19, 30, 1, 12, 1, 1, 45, 28, 9, 9, 9, 15, 19, 9, 45, 15, 1, 1, 1, 45, 15, 15, 45, 45, 45, 19, 45, 45, 45, 45, 15, 19, 9, 5, 18, 18, 9, 19, 9, 9, 5, 5, 18, 18, 20, 20, 20, 20, 20, 20, 20, 20, 18, 20, 20, 18, 18, 18, 18, 5, 18, 5, 5, 5, 5, 20, 32, 3, 32, 32, 32, 20, 5, 5, 5, 3, 32, 3, 32, 5, 9, 18, 18, 5, 18, 18, 18, 18, 18, 18, 18, 32, 18, 3, 32, 32, 32], "47": [37, 0, 22, 22, 0, 0, 0, 0, 0, 22, 22, 0, 37, 37, 0, 0, 37, 22, 22, 22, 22, 22, 22, 22, 22, 0, 37, 0, 22, 22, 22, 0, 0, 0, 22, 22, 22, 22, 7, 10, 10, 0, 0, 42, 42, 42, 24, 24, 24, 11, 24, 24, 3, 7, 42, 24, 24, 24, 11, 10, 44, 11, 3, 24, 24, 44, 44, 44, 3, 37, 24, 7, 37, 10, 46, 3, 7, 42, 42, 24, 4, 4, 4, 7, 7, 7, 4, 4, 4, 4, 4, 4, 29, 0, 7, 4, 41, 11, 41, 44, 44, 29, 7, 0, 41, 29, 46, 31, 31, 31, 31, 31, 31, 31, 35, 44, 44, 7, 7, 44, 4, 29, 44, 44, 7, 39, 9, 44, 39, 46, 14, 29, 39, 9, 39, 39, 9, 35, 46, 36, 36, 26, 32, 32, 46, 32, 13, 14, 29, 26, 13, 33, 40, 18, 40, 40, 43, 26, 13, 28, 27, 28, 25, 2, 18, 5, 25, 2, 33, 21, 30, 18, 43, 2, 33, 8, 8, 8, 8, 8, 8, 16, 21, 20, 33, 21, 18, 19, 25, 13, 32, 38, 25, 13, 13, 25, 40, 6, 6, 6, 6, 6, 6, 16, 16, 16, 16, 23, 27, 23, 6, 25, 6, 1, 6, 6, 23, 34, 34, 6, 23, 34, 23, 34, 31, 31, 17, 31, 1, 23, 1, 27, 31, 34, 17, 17, 23, 23, 23, 23, 17, 23, 23, 34, 27, 31, 31, 27, 36, 15, 36, 46, 46, 12, 12, 12, 12, 17, 23, 12, 46, 46, 4, 4, 12, 15, 36, 15, 15, 15, 15, 12, 15, 12, 36, 11, 3, 36, 36, 11, 45, 36, 36, 11, 45, 15, 45, 36, 11, 45, 36, 36, 36, 27, 36, 36, 27, 15, 36, 45, 3, 10, 10, 10, 3, 36, 3, 3, 3, 10, 10, 37, 37, 37, 37, 37, 37, 0, 37, 37, 37, 37, 37, 37, 37, 37, 10, 10, 10, 10, 10, 3, 10, 37, 0, 0, 22, 22, 0, 0, 3, 3, 10, 0, 22, 0, 0, 10, 3, 10, 10, 3, 10, 10, 37, 10, 10, 10, 10, 0, 10, 37, 22, 22, 22], "48": [13, 6, 40, 40, 6, 6, 6, 6, 6, 40, 40, 6, 6, 13, 6, 0, 18, 40, 30, 30, 40, 40, 30, 40, 30, 6, 13, 6, 40, 40, 0, 6, 6, 6, 30, 30, 30, 0, 35, 37, 18, 13, 13, 35, 35, 35, 8, 8, 8, 31, 8, 31, 37, 35, 35, 8, 31, 31, 34, 18, 37, 34, 27, 8, 8, 37, 37, 37, 3, 13, 8, 35, 13, 37, 41, 3, 35, 35, 17, 17, 17, 41, 41, 24, 35, 17, 17, 41, 41, 41, 41, 41, 41, 6, 35, 17, 41, 34, 24, 37, 37, 17, 35, 6, 17, 41, 1, 21, 21, 21, 21, 21, 20, 21, 21, 24, 24, 17, 24, 24, 1, 16, 24, 47, 35, 17, 10, 37, 38, 1, 24, 16, 10, 10, 16, 10, 21, 21, 1, 27, 28, 21, 9, 9, 39, 44, 23, 38, 38, 44, 9, 7, 15, 32, 15, 15, 22, 21, 9, 22, 36, 22, 25, 43, 32, 23, 25, 43, 7, 46, 33, 32, 5, 43, 7, 19, 19, 19, 46, 46, 19, 26, 46, 7, 7, 46, 32, 42, 23, 23, 9, 12, 25, 23, 45, 25, 9, 2, 45, 2, 2, 2, 2, 2, 26, 26, 26, 4, 5, 45, 2, 20, 45, 20, 45, 45, 4, 5, 5, 45, 4, 20, 4, 5, 20, 21, 20, 45, 5, 4, 5, 36, 14, 20, 20, 20, 4, 4, 4, 4, 4, 4, 4, 5, 36, 21, 14, 36, 28, 11, 27, 41, 41, 29, 14, 14, 14, 14, 14, 14, 11, 41, 41, 41, 29, 11, 28, 11, 36, 11, 11, 29, 11, 29, 36, 31, 37, 28, 28, 34, 28, 27, 28, 34, 29, 29, 29, 28, 34, 34, 28, 28, 28, 36, 36, 28, 36, 11, 28, 11, 27, 18, 18, 18, 37, 36, 27, 28, 37, 37, 18, 18, 13, 13, 13, 13, 13, 13, 13, 13, 13, 13, 13, 18, 13, 13, 18, 18, 18, 18, 37, 27, 18, 13, 6, 6, 40, 40, 40, 13, 37, 37, 18, 6, 0, 6, 6, 18, 27, 18, 18, 37, 18, 18, 18, 18, 18, 18, 18, 6, 18, 6, 40, 40, 40], "49": [19, 15, 24, 24, 24, 15, 15, 32, 15, 24, 24, 32, 32, 19, 4, 32, 19, 24, 47, 47, 24, 24, 47, 24, 47, 32, 19, 4, 4, 4, 24, 32, 32, 15, 24, 47, 47, 24, 38, 1, 1, 4, 4, 26, 26, 26, 26, 26, 26, 10, 10, 10, 42, 38, 26, 26, 10, 10, 33, 1, 1, 33, 42, 10, 10, 30, 1, 42, 5, 15, 26, 38, 19, 1, 46, 42, 38, 26, 43, 43, 43, 18, 18, 10, 38, 38, 43, 18, 18, 18, 18, 18, 2, 15, 38, 44, 46, 33, 30, 42, 42, 44, 38, 32, 43, 2, 46, 20, 20, 20, 20, 20, 17, 17, 20, 30, 42, 43, 10, 30, 18, 2, 30, 42, 38, 44, 22, 42, 21, 46, 30, 2, 21, 22, 44, 21, 22, 17, 46, 5, 5, 20, 48, 48, 17, 13, 11, 12, 21, 45, 13, 6, 41, 29, 41, 28, 27, 20, 13, 27, 12, 27, 23, 34, 29, 11, 23, 6, 6, 41, 40, 40, 31, 6, 6, 16, 16, 16, 41, 41, 16, 39, 0, 6, 6, 41, 34, 7, 14, 13, 48, 36, 23, 11, 11, 23, 13, 28, 35, 28, 28, 7, 28, 28, 28, 39, 39, 9, 37, 35, 35, 7, 35, 7, 35, 35, 9, 3, 37, 35, 9, 3, 9, 31, 17, 20, 17, 35, 37, 9, 37, 12, 17, 31, 25, 25, 35, 9, 9, 9, 9, 9, 9, 37, 12, 20, 20, 12, 12, 8, 5, 46, 17, 17, 25, 25, 25, 25, 9, 25, 8, 18, 18, 18, 25, 12, 12, 8, 12, 37, 8, 25, 8, 8, 12, 10, 5, 12, 5, 33, 12, 5, 12, 33, 8, 8, 8, 12, 33, 33, 12, 12, 12, 12, 12, 12, 12, 12, 33, 8, 5, 1, 1, 1, 5, 12, 5, 5, 42, 1, 1, 19, 19, 19, 19, 19, 19, 32, 19, 19, 19, 19, 32, 19, 19, 19, 1, 1, 1, 1, 1, 5, 1, 19, 32, 15, 4, 24, 24, 32, 1, 1, 1, 15, 24, 15, 32, 1, 5, 1, 1, 5, 1, 1, 19, 1, 1, 1, 1, 32, 1, 15, 24, 24, 24]}, "closest": {"2": [227, 315], "3": [196, 260, 313], "4": [103, 224, 196, 61], "5": [87, 224, 196, 103, 307], "6": [14, 268, 309, 154, 227, 87], "7": [268, 32, 154, 275, 89, 309, 209], "8": [32, 146, 154, 309, 255, 50, 90, 297], "9": [32, 189, 309, 90, 290, 184, 256, 229, 50], "10": [256, 329, 275, 172, 184, 229, 90, 338, 290, 150], "11": [90, 309, 264, 179, 237, 291, 50, 150, 172, 103, 10], "12": [309, 237, 10, 184, 285, 50, 261, 103, 189, 290, 134, 203], "13": [309, 237, 45, 90, 184, 275, 325, 256, 203, 290, 150, 172, 9], "14": [237, 309, 290, 82, 184, 103, 256, 203, 172, 134, 150, 50, 245, 10], "15": [3, 262, 188, 184, 285, 325, 47, 241, 309, 134, 150, 203, 161, 290, 254], "16": [268, 47, 150, 3, 237, 309, 184, 261, 313, 256, 134, 161, 277, 176, 203, 188], "17": [297, 203, 103, 234, 275, 184, 172, 10, 245, 134, 303, 142, 262, 45, 150, 237, 307], "18": [256, 47, 190, 309, 325, 237, 9, 82, 179, 288, 195, 245, 290, 203, 161, 223, 184, 134], "19": [325, 245, 184, 290, 230, 45, 82, 9, 237, 190, 341, 164, 172, 195, 286, 303, 275, 134, 203], "20": [184, 286, 323, 245, 241, 309, 10, 82, 179, 143, 291, 275, 32, 230, 161, 199, 134, 195, 45, 172], "21": [45, 203, 103, 188, 268, 190, 245, 184, 262, 134, 256, 303, 241, 167, 10, 140, 79, 100, 212, 179, 161], "22": [262, 303, 203, 256, 103, 195, 278, 152, 79, 108, 288, 9, 290, 45, 190, 175, 237, 134, 223, 122, 188, 171], "23": [138, 309, 241, 184, 5, 47, 291, 134, 204, 286, 150, 212, 175, 245, 116, 10, 313, 188, 262, 154, 195, 218, 159], "24": [10, 230, 122, 175, 150, 309, 108, 45, 306, 241, 134, 32, 212, 286, 262, 203, 159, 167, 323, 191, 290, 256, 56, 79], "25": [184, 100, 270, 212, 80, 306, 103, 156, 10, 360, 190, 203, 223, 108, 45, 256, 131, 241, 244, 195, 262, 133, 164, 290, 175], "26": [241, 325, 137, 179, 244, 288, 203, 32, 245, 100, 150, 56, 164, 277, 212, 230, 134, 172, 234, 82, 303, 184, 10, 195, 45, 286], "27": [159, 303, 236, 290, 164, 79, 10, 108, 286, 50, 175, 150, 256, 203, 154, 325, 234, 5, 133, 223, 90, 122, 216, 191, 45, 341, 131], "28": [234, 32, 61, 237, 184, 351, 79, 245, 164, 90, 290, 142, 100, 161, 10, 323, 189, 203, 134, 181, 268, 191, 256, 45, 154, 116, 176, 137], "29": [10, 237, 100, 176, 297, 184, 271, 45, 262, 157, 303, 205, 256, 150, 140, 164, 56, 108, 208, 325, 170, 126, 134, 234, 32, 195, 156, 79, 197], "30": [103, 146, 265, 89, 203, 184, 108, 290, 100, 254, 45, 185, 126, 230, 134, 56, 360, 163, 170, 195, 190, 10, 219, 156, 286, 242, 288, 176, 236, 167], "31": [164, 319, 270, 108, 10, 237, 100, 188, 86, 152, 46, 146, 126, 103, 61, 176, 294, 256, 162, 303, 205, 131, 172, 90, 203, 190, 184, 213, 242, 212, 243], "32": [242, 44, 286, 164, 288, 79, 32, 90, 237, 146, 306, 303, 203, 223, 176, 172, 122, 134, 234, 108, 124, 256, 150, 325, 142, 131, 188, 10, 154, 290, 48, 184], "33": [286, 303, 186, 50, 199, 262, 10, 307, 164, 156, 134, 190, 175, 290, 245, 191, 155, 45, 79, 288, 122, 32, 219, 146, 227, 223, 256, 205, 162, 325, 241, 161, 184], "34": [140, 167, 336, 236, 309, 105, 205, 245, 45, 146, 196, 256, 137, 325, 176, 154, 156, 132, 297, 184, 195, 79, 242, 122, 262, 5, 223, 10, 191, 150, 170, 164, 56, 199], "35": [288, 199, 32, 108, 290, 184, 131, 256, 152, 78, 22, 144, 100, 150, 134, 172, 56, 234, 82, 303, 122, 253, 241, 179, 214, 161, 363, 325, 306, 146, 208, 195, 205, 76, 270], "36": [243, 118, 164, 103, 137, 165, 167, 290, 341, 251, 338, 45, 199, 190, 256, 211, 87, 241, 250, 108, 56, 159, 154, 360, 134, 184, 195, 205, 262, 215, 188, 223, 10, 122, 170, 176], "37": [126, 331, 154, 32, 79, 234, 261, 241, 290, 50, 184, 328, 170, 161, 255, 203, 270, 195, 134, 223, 108, 325, 10, 176, 100, 212, 118, 282, 187, 186, 150, 143, 88, 45, 191, 289, 164], "38": [309, 241, 251, 186, 5, 176, 45, 137, 285, 195, 322, 199, 289, 10, 50, 250, 223, 134, 89, 209, 109, 159, 122, 191, 252, 205, 184, 194, 150, 170, 142, 79, 291, 257, 152, 244, 356, 117], "39": [5, 254, 306, 146, 185, 55, 242, 356, 244, 288, 122, 223, 215, 134, 90, 195, 10, 183, 152, 176, 191, 167, 286, 199, 309, 45, 143, 322, 256, 291, 161, 204, 150, 131, 168, 144, 108, 49, 181], "40": [50, 194, 323, 248, 184, 273, 216, 256, 10, 134, 156, 150, 309, 181, 190, 208, 203, 38, 167, 80, 170, 254, 70, 176, 122, 237, 185, 137, 221, 278, 262, 260, 186, 191, 145, 195, 107, 234, 161, 5], "41": [242, 325, 270, 164, 50, 280, 210, 22, 108, 154, 32, 303, 275, 90, 159, 191, 230, 135, 45, 145, 141, 134, 208, 288, 175, 237, 256, 205, 290, 170, 227, 142, 150, 306, 100, 112, 195, 79, 363, 183, 168], "42": [195, 116, 10, 255, 239, 341, 184, 197, 108, 250, 290, 128, 131, 212, 32, 218, 45, 56, 191, 159, 150, 262, 181, 171, 179, 143, 133, 224, 153, 249, 87, 205, 303, 221, 325, 146, 176, 230, 122, 186, 170, 241], "43": [363, 212, 291, 179, 341, 79, 273, 234, 126, 195, 224, 45, 325, 170, 163, 241, 319, 244, 184, 154, 32, 56, 150, 108, 191, 161, 131, 202, 35, 243, 194, 306, 288, 262, 285, 205, 303, 159, 85, 168, 256, 122, 156], "44": [121, 322, 162, 152, 341, 257, 262, 209, 244, 288, 126, 156, 10, 205, 325, 102, 108, 164, 146, 176, 122, 47, 190, 291, 303, 241, 132, 230, 338, 170, 183, 197, 286, 188, 165, 172, 224, 144, 101, 199, 161, 79, 306, 184], "45": [200, 325, 90, 244, 176, 63, 22, 116, 209, 128, 241, 195, 190, 108, 172, 205, 254, 186, 45, 184, 303, 79, 270, 221, 1, 290, 153, 134, 161, 191, 163, 363, 199, 250, 288, 25, 146, 56, 187, 341, 171, 149, 185, 162, 122], "46": [10, 286, 109, 361, 203, 309, 84, 167, 87, 306, 126, 156, 255, 176, 150, 288, 221, 209, 356, 305, 313, 164, 137, 162, 112, 122, 165, 105, 50, 191, 230, 154, 11, 184, 129, 216, 262, 208, 131, 195, 143, 170, 241, 130, 45, 291], "47": [32, 228, 167, 351, 88, 165, 210, 102, 176, 126, 303, 288, 271, 189, 147, 270, 205, 235, 164, 187, 183, 185, 10, 241, 48, 195, 157, 244, 161, 131, 170, 108, 142, 184, 223, 114, 291, 325, 191, 134, 154, 96, 54, 172, 100, 284, 251], "48": [37, 106, 199, 68, 241, 218, 5, 184, 48, 190, 133, 270, 191, 313, 255, 154, 131, 79, 360, 176, 234, 108, 159, 146, 122, 195, 205, 306, 292, 286, 35, 56, 164, 170, 288, 45, 293, 341, 148, 144, 363, 262, 187, 167, 145, 212, 185, 123], "49": [182, 303, 131, 221, 14, 306, 184, 211, 286, 241, 50, 194, 290, 150, 188, 1, 176, 232, 89, 325, 108, 128, 126, 195, 9, 256, 45, 159, 203, 153, 122, 223, 25, 288, 186, 212, 191, 230, 76, 205, 170, 185, 100, 79, 101, 149, 251, 35, 142]}}